Workbook

Sheet 01 README
A1: Hiver Technology - SEO Master Workbook
A2: Prepared 2026-08-14. Benchmarked against a supplied 253-URL competitor audit (nexly.com.au) and a live inspection of hiver.com.np.
A3: Item | B3: Detail
A4: What this workbook is | B4: An SEO, architecture and content plan for Hiver Technology (hiver.com.np), benchmarked against a real competitor site audit (nexly.com.au, 253 URLs) supplied by the client, plus a live inspection of hiver.com.np.
A5: Verification date | B5: 2026-08-14. Every SERP, competitor and site observation in this workbook was made on or before this date. Re-verify before acting on anything time-sensitive.
A6: Provenance rule | B6: Every data point carries a Source label. No search volume, keyword difficulty, CPC or backlink figure has been invented. Cells reading DATA REQUIRED must be filled from a paid tool or from Hiver before the plan is final.
A7: Source labels used | B7: [VERIFIED-SITE] observed directly on the live site | [VERIFIED-FILE] taken from the supplied Nexly audit file | [COMPETITOR-DERIVED] inferred from a competitor's actual page/title/URL choices | [STRATEGIC-JUDGEMENT] the analyst's reasoning, no metric behind it | [DATA REQUIRED] unavailable, must be sourced
A8: Cell colour convention | B8: Blue text = an input you can change (scoring weights). Yellow fill = a gap that must be filled before launch. Black text = formula or fixed research output.
A9: Which cells to edit | B9: Scoring Model!B5:B8 (the four weights, must total 100%) and the tier multipliers below them. Master Keywords columns F-H (Volume / KD / CPC) once you have Ahrefs or Semrush access. Any cell marked DATA REQUIRED. Everything else is derived.
A10: How the priority score works | B10: Master Keywords column P weights four 1-5 judgement scores and rescales to 0-100. Column Q then multiplies that by the winnability multiplier for the keyword's tier, so a head term Hiver cannot win drops to the bottom instead of topping the list on commercial intent. Sort by column Q. Change any weight or multiplier and every score recalculates. The score prioritises work; it does not predict rankings.
A11: Reading order | B11: 1. Exec Summary 2. Hiver Baseline 3. Competitor Benchmark 4. Gap Matrix 5. Master Keywords 6. URL Map 7. Page SEO 8. Content Briefs 9. everything else as needed.
A12: What this workbook does not do | B12: It does not promise rankings, does not claim tool-verified volumes, and does not plan pages for services Hiver has not confirmed it delivers. Capability-gated pages are flagged in the URL Map.
A15: Legend
A16: Blue text | B16: An input cell you can change (see Scoring Model)
A17: Yellow fill | B17: A gap that must be filled before launch - marked DATA REQUIRED
A18: Black text | B18: Formula output or fixed research finding

Sheet 02 Exec Summary
A1: Executive summary - ten findings that shape the plan
A2: Every finding is sourced. Findings 2, 3 and 7 must be resolved before any page is built.
A3: Finding | B3: Detail | C3: Source
A4: 1. The honest starting position | B4: hiver.com.np is a partially built WordPress/Elementor template, not a functioning agency site. It carries an 'Under Construction' banner, unedited demo testimonials, placeholder client-logo alt text, and nav/footer links that point to '#'. There are no service pages. Treat this as a build, not an optimisation. | C4: [VERIFIED-SITE]
A5: 2. The domain is a structural handicap | B5: .com.np is a Nepal country-code namespace. Google treats ccTLDs as a geographic signal and Search Console's international-targeting override has historically applied only to generic TLDs. Competing for US/AU/UK commercial terms from this domain adds a headwind on top of the authority gap. A gTLD decision must be made before any URL is built. | C5: [STRATEGIC-JUDGEMENT]
A6: 3. The brand name is taken | B6: 'Hiver' is an established customer-service SaaS company (hiverhq.com) with a large review and content footprint. The branded SERP is not winnable. All navigational search must be built around 'Hiver Technology'. Trademark exposure in the US/AU/UK is a question for a qualified attorney, not for this workbook. | C6: [VERIFIED-SITE]
A7: 4. The competitor proves the market is winnable | B7: Nexly runs 253 URLs: 69 templated Shopify service pages, 119 blog posts, 15 integration pages, 11 migration pages, 7 case studies. Its co-founder and SEO lead links to a Nepal LinkedIn profile while two directors link to Australian profiles. A distributed Nepal-plus-onshore team is already competing successfully for Australian Shopify work. This is the closest available model of what works. | C7: [VERIFIED-FILE]
A8: 5. The competitor's weaknesses are Hiver's openings | B8: Across all 253 Nexly URLs the audit detected no structured data at all, every page has images missing alt text, 122 titles exceed 60 characters, 31 pages have no meta description, and 27 pages are under 300 words (team pages, case studies, blog categories). Case studies average roughly 400 words despite carrying strong results. | C8: [VERIFIED-FILE]
A9: 6. Where Hiver can realistically rank first | B9: Not on head terms. The winnable ground is narrow and specific: integration and migration pairings, platform-plus-problem queries, cost and comparison questions, 'hire a dedicated developer' intent where offshore delivery is an advantage, and the vertical software categories tied to Hiver's own products. See the Winnability tier column on Master Keywords. | C9: [STRATEGIC-JUDGEMENT]
A10: 7. The Shopify plan is gated on capability | B10: The brief treats Shopify as a flagship service, but no Shopify page exists on hiver.com.np and Hiver's Shopify track record is unconfirmed. Every Shopify page in this workbook is marked capability-gated. Do not publish them until Hiver confirms delivered stores, Partner status and at least one referenceable project. | C10: [VERIFIED-SITE]
A11: 8. The overlooked asset | B11: Hiver's footer lists vertical software products (school, dental, clinic, HR management) that the original brief never mentioned. Product-category search is typically less contested than agency search and monetises directly. This deserves its own section and its own decision. | C11: [VERIFIED-SITE]
A12: 9. Distribution matters as much as ranking | B12: For agency buying in the US/AU/UK, Clutch, G2, DesignRush, GoodFirms, Upwork and the Shopify Partner directory frequently occupy the commercial SERP and are where shortlists form. Profile completion is a launch-phase task, not a later one. | C12: [STRATEGIC-JUDGEMENT]
A13: 10. What has to happen first | B13: Phase 0 is unblocking, not SEO: remove the construction banner, delete the demo testimonials and placeholder logos, fix every '#' link, resolve the domain and brand decisions, install analytics and Search Console, replace the 'superadmin' author identity. Nothing else in this workbook is worth doing before that. | C13: [VERIFIED-SITE]

Sheet 03 Hiver Baseline
A1: Hiver baseline audit - live site, verified 2026-08-14
A2: Observed directly on hiver.com.np. Re-verify before acting; the site may change.
A3: ID | B3: Area | C3: Finding | D3: Evidence | E3: Business impact | F3: Severity | G3: Owner | H3: Action
A4: B01 | B4: Trust | C4: Site displays an 'Website Still Under Construction' banner | D4: Homepage, observed 2026-08-14 | E4: Any US/AU/UK buyer who lands here disqualifies Hiver in seconds | F4: Blocker | G4: Marketing | H4: Remove banner or take the site offline until launch-ready
A5: B02 | B5: Legal / Trust | C5: Six testimonials are unedited theme demo content ('Sarah', 'John Farrel', 'John Doe Iswanto', 'Jackma Kalin', 'Darsono', 'Ismail'); copy refers to a copywriting service | D5: Homepage testimonials block | E5: Fabricated endorsements. Consumer-protection exposure with the FTC (US), ACCC (AU) and CMA/ASA (UK); severe E-E-A-T damage | F5: Blocker | G5: Founder | H5: Delete entirely. Do not rewrite. Replace only with permissioned real testimonials
A6: B03 | B6: Trust | C6: Client logo alt text reads 'Brand Name : Brand Short Description Type Here.'; one logo in the client strip is Hiver's own logo | D6: Homepage client strip | E6: Placeholder content shipped live; implies fabricated client roster | F6: Blocker | G6: Marketing | H6: Remove until real permissioned logos exist
A7: B04 | B7: Crawl / IA | C7: Almost all main nav and footer links resolve to '#' | D7: Header and footer markup | E7: No crawlable internal link graph. Existing child pages are effectively orphaned | F7: Blocker | G7: Dev | H7: Build the real URL structure and wire every nav item to it
A8: B05 | B8: Architecture | C8: No service pages exist. Live services are only listed as homepage cards: Web Applications, Mobile Apps, Responsive Websites, CRM Web Applications, UI/UX Design, Digital Marketing | D8: Homepage services block | E8: Zero commercial landing pages; nothing can rank or convert | F8: Critical | G8: Content | H8: Build the P0 service pages in the URL Map tab
A9: B06 | B9: Scope mismatch | C9: The brief's service list (Shopify, SEO services, email marketing, automations) does not exist on the live site | D9: Site vs brief comparison | E9: Plan must be a build, and Shopify/SEO pages must be capability-gated | F9: Critical | G9: Founder | H9: Confirm which services are genuinely delivered today (see Data Required tab)
A10: B07 | B10: Opportunity | C10: Footer lists products: School Management, Dental Management, Clinic Management, HR Software, Employee Management | D10: Footer products column | E10: Potentially the strongest and least contested search opportunity; absent from the brief | F10: Critical opportunity | G10: Founder | H10: Confirm product status, then build the /products/ section
A11: B08 | B11: URL structure | C11: Blog posts sit at root (e.g. /programmer-developer-and-engineer-explained/) while /insights/ also exists | D11: Homepage news block | E11: Inconsistent structure; a redirect map is required before restructuring | F11: High | G11: Dev | H11: Move posts under /insights/ with 301s; never leave both live
A12: B09 | B12: E-E-A-T | C12: Author metadata is 'superadmin' | D12: twitter:data1 meta value | E12: No human author entity; fails author-level E-E-A-T and looks unmaintained | F12: High | G12: Content | H12: Create real author profiles with credentials and byline them
A13: B10 | B13: Content quality | C13: Visible typos in live copy: 'Developemnt', 'Transfering', "help's", 'Insitagram' | D13: Homepage and footer | E13: Premium-market buyers read this as low care and low capability | F13: High | G13: Content | H13: Full copy proof before launch
A14: B11 | B14: On-page | C14: Homepage title is 'Hiver Technology | AI-Powered Software, Apps & Web Solutions' | D14: Title tag | E14: No commercial keyword, no market signal, no service specificity | F14: High | G14: SEO | H14: Rewrite per the Page SEO tab
... A21: B18 | B21: Images | C21: Hero and section imagery is generic stock (e.g. pexels files) | D21: Homepage image paths | E21: Reads as templated; no product or interface proof | F21: Medium | G21: Design | H21: Replace with real interface, product and process visuals

Sheet 04 Competitor Benchmark
A1: Competitor benchmark - nexly.com.au (253 URLs)
A2: All figures from the supplied audit file. This is the depth and structure bar Hiver is measured against.
A3: Metric | B3: Competitor | C3: Hiver today | D3: What it means for Hiver | E3: Source
A4: Total indexable URLs discovered | B4: 253 | C4: Approx. 6 reachable, most nav links dead | D4: Hiver needs a real site before it needs an SEO plan | E4: [VERIFIED-FILE] / [VERIFIED-SITE]
A5: Templated service pages | B5: 69 | C5: 0 | D5: The single biggest structural gap | E5: [VERIFIED-FILE]
A6: Median words, service page | B6: 1,281 (range 839-2,446) | C6: n/a | D6: This is the depth bar for a Hiver service page: roughly 1,200-1,600 words | E6: [VERIFIED-FILE]
A7: H2 sections per service page | B7: 11 (highly consistent) | C7: n/a | D7: Evidence of one reusable template applied at scale, not bespoke pages | E7: [VERIFIED-FILE]
A8: Blog posts | B8: 119 | C8: 2 (2024, Nepal-focused) | D8: Content programme is the competitor's main moat | E8: [VERIFIED-FILE]
A9: Median words, blog post | B9: 1,837 (range 519-2,471) | C9: n/a | D9: Depth bar for Hiver insight articles | E9: [VERIFIED-FILE]
A10: Integration pages | B10: 15 (Xero, MYOB, NetSuite, SAP, Cin7, HubSpot, Salesforce, Klaviyo, Dynamics 365, Akeneo, Shippit, Starshipit, Australia Post, 3PL/WMS) | C10: 0 | D10: Platform-plus-system pairings are the clearest winnable long-tail pattern in the whole dataset | E10: [VERIFIED-FILE]
A11: Median words, integration page | B11: 968 (8-9 H2s) | C11: n/a | D11: Shorter than service pages; a realistic first content target | E11: [VERIFIED-FILE]
A12: Migration pages | B12: 11 (Magento, Adobe Commerce, BigCommerce, WooCommerce, PrestaShop, OpenCart, SFCC, custom platform, theme, Shopify-to-Plus) | C12: 0 | D12: 'X to Y migration' is a repeatable, high-intent page pattern | E12: [VERIFIED-FILE]
A13: Case studies | B13: 7 (EzyDog AU/NZ/UK/EU/USA, Town & Country Covers) | C13: 0 | D13: One client family carries five of seven case studies | E13: [VERIFIED-FILE]
A14: Median words, case study | B14: 399 (range 344-747) | C14: n/a | D14: Thin. Hiver can beat this on depth with a single well-documented project | E14: [VERIFIED-FILE]
... A29: Case study proof style | B29: Named client, named markets, specific outcome claims, service tags, live store link | C29: None | D29: Hiver cannot match this until it has permissioned client data. This is the critical blocker | E29: [VERIFIED-FILE]

Sheet 05 Page Archetypes
A1: Page archetypes observed in the competitor set
A2: Extracted from real heading structures. Use as templates; do not copy wording.
A3: Page type | B3: Example URL | C3: Words | D3: H2 count | E3: Section sequence | F3: Why it works / how to beat it | G3: Source
A4: Service page | B4: /services/shopify-development/ | C4: 1,580 | D4: 12 | E4: H1 outcome statement | Problem question | Choose your path | Choose approach | What we build | What you get, stage by stage | How we run a build | Tested before it ships | What it costs | FAQs | Related services | Intent-matched CTA | Site-wide CTA | F4: Cost section on a service page is unusual and high-value. Problem-first H2 as a question. Two CTAs: one page-specific, one site-wide. | G4: [VERIFIED-FILE]
A5: Migration page | B5: /migrations/magento-to-shopify/ | C5: 1,066 | D5: 8 | E5: H1 'X to Y migration' | Why brands leave X | What moves across | What the migration covers | How it runs | FAQs | Related services | Assessment CTA | Site-wide CTA | F5: 'What moves across' is the buyer's real question and the reason this page type converts. Repeatable per source platform. | G5: [VERIFIED-FILE]
A6: Integration page | B6: /integrations/shopify-xero/ | C6: 985 | D6: 9 | E6: H1 'A + B integration' | The manual cost of not integrating | What syncs, which way | What a proper integration covers | How we build it | What it costs | FAQs | Related services | Scope CTA | Site-wide CTA | F6: Cheapest page type to produce (roughly 950 words) and the most obviously winnable pattern. 'What syncs, which way' is the differentiator. | G6: [VERIFIED-FILE]
A7: Case study | B7: /case-studies/ezydog-au/ | C7: 506 | D7: 3 (mostly H3 steps) | E7: H1 outcome sentence | Metric strip | Service tags | The challenge | What we did (numbered steps) | The outcome | More case studies | 'Could your store be next' CTA | F7: Short but effective because the metrics are specific. Hiver should use the same skeleton with more depth and verified numbers only. | G7: [VERIFIED-FILE]
A8: Homepage | B8: / | C8: 3,136 | D8: 13 | E8: Outcome H1 | Client logos | Value proposition | Primary service depth | Why the approach | Comparison table | What's included | Tech stack | Process | Proof | Named team with photos | FAQ | CTA | F8: Named team on the homepage is a deliberate trust device for a remote-delivery buyer. Hiver should copy the intent, not the layout. | G8: [VERIFIED-FILE]
A9: Enquiry page | B9: /project-enquiry/ | C9: 862 | D9: 5 | E9: Three steps: Project (multi-select services) | Business (URL, platform, revenue band, budget band, start date) | Contact, with conditional per-service qualifier blocks | F9: Qualification happens in the form, not in a sales call. This is the single most copyable asset in the competitor set. | G9: [VERIFIED-FILE]

Sheet 06 Gap Matrix
A1: Competitor gap matrix
A2: Opportunity ranks the size of the prize; Effort ranks what it costs Hiver to close.
A3: Topic / asset | B3: Hiver | C3: Competitor | D3: Gap type | E3: Opportunity | F3: Effort | G3: Priority | H3: Recommendation
A4: Commercial service pages | B4: None | C4: 69 templated pages | D4: Service | E4: High | F4: High | G4: P0 | H4: Build 8-10 genuinely differentiated service pages first. Do not attempt 69.
A5: Integration pages (platform + system) | B5: None | C5: 15 pages, ~968 words each | D5: Content / long-tail | E5: High | F5: Medium | G5: P1 | H5: Strongest winnable pattern in the dataset. Build only for systems Hiver has actually integrated.
A6: Migration pages (X to Y) | B6: None | C6: 11 pages | D6: Content / high intent | E6: High | F6: Medium | G6: P1 | H6: Start with WordPress/WooCommerce migrations where Hiver's capability is most credible.
A7: Structured data | B7: None | C7: None detected on 253 URLs | D7: Technical | E7: Medium | F7: Low | G7: P0 | H7: Immediate differentiator. Organization, WebSite, BreadcrumbList, Service, Article, Person, SoftwareApplication.
A8: Image alt text | B8: Placeholder text | C8: Missing on all 253 pages | D8: Technical / accessibility | E8: Medium | F8: Low | G8: P0 | H8: Trivial to win. Also required for the WCAG position below.
A9: Accessibility (WCAG 2.2 AA) | B9: Unknown | C9: Sells the service; fails basic alt text | D9: Trust / technical | E9: Medium | F9: Medium | G9: P1 | H9: Compliance on Hiver's own site makes the claim credible and matters for AU/UK procurement.
A10: Title tag discipline | B10: Weak | C10: 122 of 253 titles over 60 characters | D10: On-page / CTR | E10: Medium | F10: Low | G10: P0 | H10: Keep every title under 60 characters. See Page SEO tab.
A11: Case studies with verified metrics | B11: None | C11: 7, thin but specific | D11: Proof | E11: Critical | F11: High | G11: P0 (blocked) | H11: The hard blocker. One deeply documented, permissioned project beats seven thin ones.
A12: Named team with credentials | B12: Team page exists, thin | C12: 8 profiles, median 123 words | D12: Trust | E12: High | F12: Low | G12: P0 | H12: Beat this easily: real photos, real experience, real specialisms, linked LinkedIn profiles.
A13: Qualified enquiry form | B13: 'Get a Quote' link | C13: 3-step conditional qualifier | D13: Conversion | E13: High | F13: Medium | G13: P0 | H13: Adopt the pattern. See Conversion tab for the recommended field set.
A14: Intent-matched CTAs | B14: One generic CTA | C14: 7+ distinct CTA framings | D14: Conversion | E14: Medium | F14: Low | G14: P0 | H14: Match the CTA to page intent: audit, assessment, scope, discovery call.
... A23: Thin category archives | B23: None | C23: 16 thin indexable categories | D23: Technical | E23: n/a | F23: n/a | G23: Avoid | H23: Do not copy. Noindex thin archives or give them real introductory content.

Sheet 07 Scoring Model
A1: Scoring model - edit the weights, every keyword score recalculates
A2: Blue cells are inputs. The four weights must total 100%. Winnability is not a fifth weight - it is a multiplier applied after the weighted score, so an unwinnable keyword cannot be scored into the launch plan by high commercial intent alone.
A4: Factor | B4: Weight | C4: What it measures
A5: Commercial intent | B5: 0.35 | C5: How close the searcher is to paying someone
A6: Business value / capability fit | B6: 0.3 | C6: Deal size, and whether Hiver can genuinely deliver it today
A7: Search volume proxy | B7: 0.2 | C7: 1-5 judgement until real tool data replaces it
A8: Strategic relevance | B8: 0.15 | C8: Cluster and positioning value beyond the single keyword
A9: Total | B9: =SUM(B5:B8) -> 1 | C9: Must equal 100%
A12: Winnability tier table - the multiplier applied to the weighted score
A13: Tier | B13: Multiplier | C13: Meaning | D13: How to recognise it in the SERP
A14: A | B14: 1 | C14: Winnable in 0-6 months | D14: Top 10 contains thin, off-intent or non-agency results. Usually 4+ word specific phrases. Target these now.
A15: B | B15: 0.8 | C15: Winnable in 6-12 months with depth plus some links | D15: Top 10 is mostly mid-authority agencies with adequate but beatable pages.
A16: C | B16: 0.55 | C16: Winnable only with 12-24 months of authority investment | D16: Top 10 is high-authority or directory-dominated. Build the page for coverage, but do not bet the launch on the keyword.
A17: D | B17: 0.25 | C17: Not winnable as an organic bet | D17: Directory- or incumbent-locked. The page may still be needed for coverage; win the customer through paid, directories, partnerships or outbound instead.
A20: Method note
A21: Method: Weighted score = (commercial intent x W1 + business value x W2 + volume proxy x W3 + strategic relevance x W4) x 20, giving 0-100. Priority score = weighted score x the winnability multiplier for that keyword's tier. This is deliberate: a Tier D head term with perfect commercial intent lands near the bottom, which is the correct answer for a low-authority domain. The four 1-5 inputs on the Master Keywords tab are the analyst's judgement, labelled [STRATEGIC-JUDGEMENT] unless the source column says otherwise. They are not tool metrics. Replace the volume proxy with real data as soon as an Ahrefs or Semrush seat exists, then re-read the priority order. Rank band reads the keyword as an organic bet, not the page. A page can still be worth building for coverage while its head keyword is scored 'do not chase' - see the URL Map, where several such pages are P0.

Sheet 08 Master Keywords
A1: Master keyword universe
A2: No volume, difficulty or CPC figure has been invented. Columns F-H are yellow because they require a paid tool. Columns J-M are judgement scores. Column P is the weighted score; column Q multiplies it by the winnability tier, so unwinnable keywords cannot climb the list on commercial intent alone. Sort by column Q.
A3: Keyword | B3: Intent | C3: Country | D3: Target URL | E3: Page type | F3: Volume | G3: KD | H3: CPC | I3: Metric source | J3: Commercial intent (1-5) | K3: Business value (1-5) | L3: Volume proxy (1-5) | M3: Strategic relevance (1-5) | N3: Winnability tier | O3: Tier multiplier | P3: Weighted score | Q3: Priority score (0-100) | R3: Rank band as an organic bet | S3: Evidence source | T3: Note
A4: custom web application development | B4: Transactional | C4: US | D4: /services/web-application-development/ | E4: Service | F4: DATA REQUIRED | G4: DATA REQUIRED | H4: DATA REQUIRED | I4: [DATA REQUIRED - PAID TOOL] | J4: 5 | K4: 5 | L4: 4 | M4: 5 | N4: C | O4: =IFERROR(INDEX('07 Scoring Model'!$B$14:$B$17,MATCH(N4,'07 Scoring Model'!$A$14:$A$17,0)),0) -> 0.55 | P4: =ROUND((J4*'07 Scoring Model'!$B$5 + K4*'07 Scoring Model'!$B$6 + L4*'07 Scoring Model'!$B$7 + M4*'07 Scoring Model'!$B$8)*20,1) -> 96 | Q4: =ROUND(P4*O4,1) -> 52.8 | R4: =IF(Q4>=70,"1 - Target now",IF(Q4>=55,"2 - Target next",IF(Q4>=40,"3 - Support only",IF(Q4>=28,"4 - Defer","5 - Do not chase organically")))) -> 3 - Support only | S4: [COMPETITOR-DERIVED] | T4: Head term; agency-dominated. Support page, not a first win
A5: custom web application development company | B5: Transactional | C5: US | D5: /services/web-application-development/ | E5: Service | F5: DATA REQUIRED | G5: DATA REQUIRED | H5: DATA REQUIRED | I5: [DATA REQUIRED - PAID TOOL] | J5: 5 | K5: 5 | L5: 3 | M5: 5 | N5: C | O5: =IFERROR(INDEX('07 Scoring Model'!$B$14:$B$17,MATCH(N5,'07 Scoring Model'!$A$14:$A$17,0)),0) -> 0.55 | P5: =ROUND((J5*'07 Scoring Model'!$B$5 + K5*'07 Scoring Model'!$B$6 + L5*'07 Scoring Model'!$B$7 + M5*'07 Scoring Model'!$B$8)*20,1) -> 92 | Q5: =ROUND(P5*O5,1) -> 50.6 | R5: =IF(Q5>=70,"1 - Target now",IF(Q5>=55,"2 - Target next",IF(Q5>=40,"3 - Support only",IF(Q5>=28,"4 - Defer","5 - Do not chase organically")))) -> 3 - Support only | S5: [STRATEGIC-JUDGEMENT] | T5: Same intent as above; do not build a separate page
A6: web application development services | B6: Transactional | C6: UK | D6: /services/web-application-development/ | E6: Service | F6: DATA REQUIRED | G6: DATA REQUIRED | H6: DATA REQUIRED | I6: [DATA REQUIRED - PAID TOOL] | J6: 5 | K6: 5 | L6: 3 | M6: 4 | N6: C | O6: =IFERROR(INDEX('07 Scoring Model'!$B$14:$B$17,MATCH(N6,'07 Scoring Model'!$A$14:$A$17,0)),0) -> 0.55 | P6: =ROUND((J6*'07 Scoring Model'!$B$5 + K6*'07 Scoring Model'!$B$6 + L6*'07 Scoring Model'!$B$7 + M6*'07 Scoring Model'!$B$8)*20,1) -> 89 | Q6: =ROUND(P6*O6,1) -> 49 | R6: =IF(Q6>=70,"1 - Target now",IF(Q6>=55,"2 - Target next",IF(Q6>=40,"3 - Support only",IF(Q6>=28,"4 - Defer","5 - Do not chase organically")))) -> 3 - Support only | S6: [STRATEGIC-JUDGEMENT]
A7: custom crm development | B7: Transactional | C7: US | D7: /services/crm-development/ | E7: Service | F7: DATA REQUIRED | G7: DATA REQUIRED | H7: DATA REQUIRED | I7: [DATA REQUIRED - PAID TOOL] | J7: 5 | K7: 5 | L7: 3 | M7: 5 | N7: B | O7: =IFERROR(INDEX('07 Scoring Model'!$B$14:$B$17,MATCH(N7,'07 Scoring Model'!$A$14:$A$17,0)),0) -> 0.8 | P7: =ROUND((J7*'07 Scoring Model'!$B$5 + K7*'07 Scoring Model'!$B$6 + L7*'07 Scoring Model'!$B$7 + M7*'07 Scoring Model'!$B$8)*20,1) -> 92 | Q7: =ROUND(P7*O7,1) -> 73.6 | R7: =IF(Q7>=70,"1 - Target now",IF(Q7>=55,"2 - Target next",IF(Q7>=40,"3 - Support only",IF(Q7>=28,"4 - Defer","5 - Do not chase organically")))) -> 1 - Target now | S7: [VERIFIED-SITE] | T7: Hiver already lists CRM web apps as a live service
A8: custom crm software development company | B8: Transactional | C8: US | D8: /services/crm-development/ | E8: Service | F8: DATA REQUIRED | G8: DATA REQUIRED | H8: DATA REQUIRED | I8: [DATA REQUIRED - PAID TOOL] | J8: 5 | K8: 5 | L8: 3 | M8: 4 | N8: B | O8: =IFERROR(INDEX('07 Scoring Model'!$B$14:$B$17,MATCH(N8,'07 Scoring Model'!$A$14:$A$17,0)),0) -> 0.8 | P8: =ROUND((J8*'07 Scoring Model'!$B$5 + K8*'07 Scoring Model'!$B$6 + L8*'07 Scoring Model'!$B$7 + M8*'07 Scoring Model'!$B$8)*20,1) -> 89 | Q8: =ROUND(P8*O8,1) -> 71.2 | R8: =IF(Q8>=70,"1 - Target now",IF(Q8>=55,"2 - Target next",IF(Q8>=40,"3 - Support only",IF(Q8>=28,"4 - Defer","5 - Do not chase organically")))) -> 1 - Target now | S8: [STRATEGIC-JUDGEMENT]
A9: crm integration services | B9: Commercial | C9: UK | D9: /services/crm-development/ | E9: Service | F9: DATA REQUIRED | G9: DATA REQUIRED | H9: DATA REQUIRED | I9: [DATA REQUIRED - PAID TOOL] | J9: 4 | K9: 4 | L9: 3 | M9: 4 | N9: B | O9: =IFERROR(INDEX('07 Scoring Model'!$B$14:$B$17,MATCH(N9,'07 Scoring Model'!$A$14:$A$17,0)),0) -> 0.8 | P9: =ROUND((J9*'07 Scoring Model'!$B$5 + K9*'07 Scoring Model'!$B$6 + L9*'07 Scoring Model'!$B$7 + M9*'07 Scoring Model'!$B$8)*20,1) -> 76 | Q9: =ROUND(P9*O9,1) -> 60.8 | R9: =IF(Q9>=70,"1 - Target now",IF(Q9>=55,"2 - Target next",IF(Q9>=40,"3 - Support only",IF(Q9>=28,"4 - Defer","5 - Do not chase organically")))) -> 2 - Target next | S9: [STRATEGIC-JUDGEMENT]
A10: build a custom crm instead of salesforce | B10: Informational | C10: US | D10: /insights/custom-crm-vs-off-the-shelf/ | E10: Insight | F10: DATA REQUIRED | G10: DATA REQUIRED | H10: DATA REQUIRED | I10: [DATA REQUIRED - PAID TOOL] | J10: 3 | K10: 4 | L10: 2 | M10: 4 | N10: A | O10: =IFERROR(INDEX('07 Scoring Model'!$B$14:$B$17,MATCH(N10,'07 Scoring Model'!$A$14:$A$17,0)),0) -> 1 | P10: =ROUND((J10*'07 Scoring Model'!$B$5 + K10*'07 Scoring Model'!$B$6 + L10*'07 Scoring Model'!$B$7 + M10*'07 Scoring Model'!$B$8)*20,1) -> 65 | Q10: =ROUND(P10*O10,1) -> 65 | R10: =IF(Q10>=70,"1 - Target now",IF(Q10>=55,"2 - Target next",IF(Q10>=40,"3 - Support only",IF(Q10>=28,"4 - Defer","5 - Do not chase organically")))) -> 2 - Target next | S10: [STRATEGIC-JUDGEMENT] | T10: Decision-stage question, low competition
A11: custom crm development cost | B11: Commercial | C11: US | D11: /insights/custom-crm-development-cost/ | E11: Insight | F11: DATA REQUIRED | G11: DATA REQUIRED | H11: DATA REQUIRED | I11: [DATA REQUIRED - PAID TOOL] | J11: 5 | K11: 5 | L11: 3 | M11: 5 | N11: A | O11: =IFERROR(INDEX('07 Scoring Model'!$B$14:$B$17,MATCH(N11,'07 Scoring Model'!$A$14:$A$17,0)),0) -> 1 | P11: =ROUND((J11*'07 Scoring Model'!$B$5 + K11*'07 Scoring Model'!$B$6 + L11*'07 Scoring Model'!$B$7 + M11*'07 Scoring Model'!$B$8)*20,1) -> 92 | Q11: =ROUND(P11*O11,1) -> 92 | R11: =IF(Q11>=70,"1 - Target now",IF(Q11>=55,"2 - Target next",IF(Q11>=40,"3 - Support only",IF(Q11>=28,"4 - Defer","5 - Do not chase organically")))) -> 1 - Target now | S11: [COMPETITOR-DERIVED] | T11: Cost content ranks and pre-qualifies. Needs Hiver's real bands
A12: hire dedicated development team | B12: Transactional | C12: US | D12: /services/dedicated-development-team/ | E12: Service | F12: DATA REQUIRED | G12: DATA REQUIRED | H12: DATA REQUIRED | I12: [DATA REQUIRED - PAID TOOL] | J12: 5 | K12: 5 | L12: 3 | M12: 5 | N12: B | O12: =IFERROR(INDEX('07 Scoring Model'!$B$14:$B$17,MATCH(N12,'07 Scoring Model'!$A$14:$A$17,0)),0) -> 0.8 | P12: =ROUND((J12*'07 Scoring Model'!$B$5 + K12*'07 Scoring Model'!$B$6 + L12*'07 Scoring Model'!$B$7 + M12*'07 Scoring Model'!$B$8)*20,1) -> 92 | Q12: =ROUND(P12*O12,1) -> 73.6 | R12: =IF(Q12>=70,"1 - Target now",IF(Q12>=55,"2 - Target next",IF(Q12>=40,"3 - Support only",IF(Q12>=28,"4 - Defer","5 - Do not chase organically")))) -> 1 - Target now | S12: [STRATEGIC-JUDGEMENT] | T12: The one position where Hiver's structure is an advantage
A13: hire dedicated wordpress developer | B13: Transactional | C13: US | D13: /services/dedicated-development-team/ | E13: Service | F13: DATA REQUIRED | G13: DATA REQUIRED | H13: DATA REQUIRED | I13: [DATA REQUIRED - PAID TOOL] | J13: 5 | K13: 5 | L13: 3 | M13: 5 | N13: A | O13: =IFERROR(INDEX('07 Scoring Model'!$B$14:$B$17,MATCH(N13,'07 Scoring Model'!$A$14:$A$17,0)),0) -> 1 | P13: =ROUND((J13*'07 Scoring Model'!$B$5 + K13*'07 Scoring Model'!$B$6 + L13*'07 Scoring Model'!$B$7 + M13*'07 Scoring Model'!$B$8)*20,1) -> 92 | Q13: =ROUND(P13*O13,1) -> 92 | R13: =IF(Q13>=70,"1 - Target now",IF(Q13>=55,"2 - Target next",IF(Q13>=40,"3 - Support only",IF(Q13>=28,"4 - Defer","5 - Do not chase organically")))) -> 1 - Target now | S13: [STRATEGIC-JUDGEMENT] | T13: Long-tail hire intent, weaker SERP
A14: hire offshore development team | B14: Transactional | C14: UK | D14: /services/dedicated-development-team/ | E14: Service | F14: DATA REQUIRED | G14: DATA REQUIRED | H14: DATA REQUIRED | I14: [DATA REQUIRED - PAID TOOL] | J14: 5 | K14: 4 | L14: 3 | M14: 4 | N14: B | O14: =IFERROR(INDEX('07 Scoring Model'!$B$14:$B$17,MATCH(N14,'07 Scoring Model'!$A$14:$A$17,0)),0) -> 0.8 | P14: =ROUND((J14*'07 Scoring Model'!$B$5 + K14*'07 Scoring Model'!$B$6 + L14*'07 Scoring Model'!$B$7 + M14*'07 Scoring Model'!$B$8)*20,1) -> 83 | Q14: =ROUND(P14*O14,1) -> 66.4 | R14: =IF(Q14>=70,"1 - Target now",IF(Q14>=55,"2 - Target next",IF(Q14>=40,"3 - Support only",IF(Q14>=28,"4 - Defer","5 - Do not chase organically")))) -> 2 - Target next | S14: [STRATEGIC-JUDGEMENT] | T14: Buyer has already accepted the model
A15: dedicated developer monthly cost | B15: Commercial | C15: US | D15: /insights/dedicated-developer-cost/ | E15: Insight | F15: DATA REQUIRED | G15: DATA REQUIRED | H15: DATA REQUIRED | I15: [DATA REQUIRED - PAID TOOL] | J15: 5 | K15: 4 | L15: 2 | M15: 4 | N15: A | O15: =IFERROR(INDEX('07 Scoring Model'!$B$14:$B$17,MATCH(N15,'07 Scoring Model'!$A$14:$A$17,0)),0) -> 1 | P15: =ROUND((J15*'07 Scoring Model'!$B$5 + K15*'07 Scoring Model'!$B$6 + L15*'07 Scoring Model'!$B$7 + M15*'07 Scoring Model'!$B$8)*20,1) -> 79 | Q15: =ROUND(P15*O15,1) -> 79 | R15: =IF(Q15>=70,"1 - Target now",IF(Q15>=55,"2 - Target next",IF(Q15>=40,"3 - Support only",IF(Q15>=28,"4 - Defer","5 - Do not chase organically")))) -> 1 - Target now | S15: [STRATEGIC-JUDGEMENT] | T15: Requires real rate bands from Hiver
A16: offshore vs onshore development agency | B16: Commercial | C16: AU | D16: /insights/offshore-vs-onshore-development/ | E16: Insight | F16: DATA REQUIRED | G16: DATA REQUIRED | H16: DATA REQUIRED | I16: [DATA REQUIRED - PAID TOOL] | J16: 4 | K16: 4 | L16: 2 | M16: 5 | N16: A | O16: =IFERROR(INDEX('07 Scoring Model'!$B$14:$B$17,MATCH(N16,'07 Scoring Model'!$A$14:$A$17,0)),0) -> 1 | P16: =ROUND((J16*'07 Scoring Model'!$B$5 + K16*'07 Scoring Model'!$B$6 + L16*'07 Scoring Model'!$B$7 + M16*'07 Scoring Model'!$B$8)*20,1) -> 75 | Q16: =ROUND(P16*O16,1) -> 75 | R16: =IF(Q16>=70,"1 - Target now",IF(Q16>=55,"2 - Target next",IF(Q16>=40,"3 - Support only",IF(Q16>=28,"4 - Defer","5 - Do not chase organically")))) -> 1 - Target now | S16: [VERIFIED-FILE] | T16: Competitor markets against offshoring; answer it honestly
A17: wordpress development company | B17: Transactional | C17: US | D17: /services/wordpress-development/ | E17: Service | F17: DATA REQUIRED | G17: DATA REQUIRED | H17: DATA REQUIRED | I17: [DATA REQUIRED - PAID TOOL] | J17: 5 | K17: 5 | L17: 4 | M17: 5 | N17: C | O17: =IFERROR(INDEX('07 Scoring Model'!$B$14:$B$17,MATCH(N17,'07 Scoring Model'!$A$14:$A$17,0)),0) -> 0.55 | P17: =ROUND((J17*'07 Scoring Model'!$B$5 + K17*'07 Scoring Model'!$B$6 + L17*'07 Scoring Model'!$B$7 + M17*'07 Scoring Model'!$B$8)*20,1) -> 96 | Q17: =ROUND(P17*O17,1) -> 52.8 | R17: =IF(Q17>=70,"1 - Target now",IF(Q17>=55,"2 - Target next",IF(Q17>=40,"3 - Support only",IF(Q17>=28,"4 - Defer","5 - Do not chase organically")))) -> 3 - Support only | S17: [COMPETITOR-DERIVED] | T17: Head term, heavily contested
A18: wordpress development agency | B18: Transactional | C18: UK | D18: /services/wordpress-development/ | E18: Service | F18: DATA REQUIRED | G18: DATA REQUIRED | H18: DATA REQUIRED | I18: [DATA REQUIRED - PAID TOOL] | J18: 5 | K18: 5 | L18: 3 | M18: 4 | N18: C | O18: =IFERROR(INDEX('07 Scoring Model'!$B$14:$B$17,MATCH(N18,'07 Scoring Model'!$A$14:$A$17,0)),0) -> 0.55 | P18: =ROUND((J18*'07 Scoring Model'!$B$5 + K18*'07 Scoring Model'!$B$6 + L18*'07 Scoring Model'!$B$7 + M18*'07 Scoring Model'!$B$8)*20,1) -> 89 | Q18: =ROUND(P18*O18,1) -> 49 | R18: =IF(Q18>=70,"1 - Target now",IF(Q18>=55,"2 - Target next",IF(Q18>=40,"3 - Support only",IF(Q18>=28,"4 - Defer","5 - Do not chase organically")))) -> 3 - Support only | S18: [STRATEGIC-JUDGEMENT] | T18: Same page; do not split
A19: headless wordpress development | B19: Transactional | C19: US | D19: /services/wordpress-development/headless-wordpress/ | E19: Sub-service | F19: DATA REQUIRED | G19: DATA REQUIRED | H19: DATA REQUIRED | I19: [DATA REQUIRED - PAID TOOL] | J19: 4 | K19: 4 | L19: 2 | M19: 4 | N19: B | O19: =IFERROR(INDEX('07 Scoring Model'!$B$14:$B$17,MATCH(N19,'07 Scoring Model'!$A$14:$A$17,0)),0) -> 0.8 | P19: =ROUND((J19*'07 Scoring Model'!$B$5 + K19*'07 Scoring Model'!$B$6 + L19*'07 Scoring Model'!$B$7 + M19*'07 Scoring Model'!$B$8)*20,1) -> 72 | Q19: =ROUND(P19*O19,1) -> 57.6 | R19: =IF(Q19>=70,"1 - Target now",IF(Q19>=55,"2 - Target next",IF(Q19>=40,"3 - Support only",IF(Q19>=28,"4 - Defer","5 - Do not chase organically")))) -> 2 - Target next | S19: [STRATEGIC-JUDGEMENT] | T19: Technical specificity narrows the field
A20: wordpress maintenance and support plans | B20: Transactional | C20: AU | D20: /services/wordpress-maintenance/ | E20: Service | F20: DATA REQUIRED | G20: DATA REQUIRED | H20: DATA REQUIRED | I20: [DATA REQUIRED - PAID TOOL] | J20: 5 | K20: 4 | L20: 3 | M20: 4 | N20: A | O20: =IFERROR(INDEX('07 Scoring Model'!$B$14:$B$17,MATCH(N20,'07 Scoring Model'!$A$14:$A$17,0)),0) -> 1 | P20: =ROUND((J20*'07 Scoring Model'!$B$5 + K20*'07 Scoring Model'!$B$6 + L20*'07 Scoring Model'!$B$7 + M20*'07 Scoring Model'!$B$8)*20,1) -> 83 | Q20: =ROUND(P20*O20,1) -> 83 | R20: =IF(Q20>=70,"1 - Target now",IF(Q20>=55,"2 - Target next",IF(Q20>=40,"3 - Support only",IF(Q20>=28,"4 - Defer","5 - Do not chase organically")))) -> 1 - Target now | S20: [COMPETITOR-DERIVED] | T20: Retainer revenue; competitor proves the retainer page pattern
A21: elementor to custom theme migration | B21: Transactional | C21: US | D21: /services/wordpress-development/elementor-to-custom-theme/ | E21: Sub-service | F21: DATA REQUIRED | G21: DATA REQUIRED | H21: DATA REQUIRED | I21: [DATA REQUIRED - PAID TOOL] | J21: 4 | K21: 4 | L21: 2 | M21: 4 | N21: A | O21: =IFERROR(INDEX('07 Scoring Model'!$B$14:$B$17,MATCH(N21,'07 Scoring Model'!$A$14:$A$17,0)),0) -> 1 | P21: =ROUND((J21*'07 Scoring Model'!$B$5 + K21*'07 Scoring Model'!$B$6 + L21*'07 Scoring Model'!$B$7 + M21*'07 Scoring Model'!$B$8)*20,1) -> 72 | Q21: =ROUND(P21*O21,1) -> 72 | R21: =IF(Q21>=70,"1 - Target now",IF(Q21>=55,"2 - Target next",IF(Q21>=40,"3 - Support only",IF(Q21>=28,"4 - Defer","5 - Do not chase organically")))) -> 1 - Target now | S21: [VERIFIED-SITE] | T21: Hiver has direct experience of this problem on its own site
A22: wordpress site slow core web vitals fix | B22: Commercial | C22: UK | D22: /services/wordpress-performance-optimisation/ | E22: Service | F22: DATA REQUIRED | G22: DATA REQUIRED | H22: DATA REQUIRED | I22: [DATA REQUIRED - PAID TOOL] | J22: 4 | K22: 4 | L22: 3 | M22: 4 | N22: A | O22: =IFERROR(INDEX('07 Scoring Model'!$B$14:$B$17,MATCH(N22,'07 Scoring Model'!$A$14:$A$17,0)),0) -> 1 | P22: =ROUND((J22*'07 Scoring Model'!$B$5 + K22*'07 Scoring Model'!$B$6 + L22*'07 Scoring Model'!$B$7 + M22*'07 Scoring Model'!$B$8)*20,1) -> 76 | Q22: =ROUND(P22*O22,1) -> 76 | R22: =IF(Q22>=70,"1 - Target now",IF(Q22>=55,"2 - Target next",IF(Q22>=40,"3 - Support only",IF(Q22>=28,"4 - Defer","5 - Do not chase organically")))) -> 1 - Target now | S22: [STRATEGIC-JUDGEMENT] | T22: Problem-led, high intent, weak SERPs
A23: wordpress to webflow or custom which is better | B23: Informational | C23: US | D23: /insights/wordpress-vs-webflow-vs-custom/ | E23: Insight | F23: DATA REQUIRED | G23: DATA REQUIRED | H23: DATA REQUIRED | I23: [DATA REQUIRED - PAID TOOL] | J23: 3 | K23: 3 | L23: 2 | M23: 3 | N23: A | O23: =IFERROR(INDEX('07 Scoring Model'!$B$14:$B$17,MATCH(N23,'07 Scoring Model'!$A$14:$A$17,0)),0) -> 1 | P23: =ROUND((J23*'07 Scoring Model'!$B$5 + K23*'07 Scoring Model'!$B$6 + L23*'07 Scoring Model'!$B$7 + M23*'07 Scoring Model'!$B$8)*20,1) -> 56 | Q23: =ROUND(P23*O23,1) -> 56 | R23: =IF(Q23>=70,"1 - Target now",IF(Q23>=55,"2 - Target next",IF(Q23>=40,"3 - Support only",IF(Q23>=28,"4 - Defer","5 - Do not chase organically")))) -> 2 - Target next | S23: [STRATEGIC-JUDGEMENT]
A24: wordpress website cost | B24: Commercial | C24: AU | D24: /insights/wordpress-website-cost/ | E24: Insight | F24: DATA REQUIRED | G24: DATA REQUIRED | H24: DATA REQUIRED | I24: [DATA REQUIRED - PAID TOOL] | J24: 4 | K24: 4 | L24: 4 | M24: 4 | N24: A | O24: =IFERROR(INDEX('07 Scoring Model'!$B$14:$B$17,MATCH(N24,'07 Scoring Model'!$A$14:$A$17,0)),0) -> 1 | P24: =ROUND((J24*'07 Scoring Model'!$B$5 + K24*'07 Scoring Model'!$B$6 + L24*'07 Scoring Model'!$B$7 + M24*'07 Scoring Model'!$B$8)*20,1) -> 80 | Q24: =ROUND(P24*O24,1) -> 80 | R24: =IF(Q24>=70,"1 - Target now",IF(Q24>=55,"2 - Target next",IF(Q24>=40,"3 - Support only",IF(Q24>=28,"4 - Defer","5 - Do not chase organically")))) -> 1 - Target now | S24: [COMPETITOR-DERIVED]
A25: woocommerce development agency | B25: Transactional | C25: UK | D25: /services/woocommerce-development/ | E25: Service | F25: DATA REQUIRED | G25: DATA REQUIRED | H25: DATA REQUIRED | I25: [DATA REQUIRED - PAID TOOL] | J25: 5 | K25: 4 | L25: 3 | M25: 4 | N25: B | O25: =IFERROR(INDEX('07 Scoring Model'!$B$14:$B$17,MATCH(N25,'07 Scoring Model'!$A$14:$A$17,0)),0) -> 0.8 | P25: =ROUND((J25*'07 Scoring Model'!$B$5 + K25*'07 Scoring Model'!$B$6 + L25*'07 Scoring Model'!$B$7 + M25*'07 Scoring Model'!$B$8)*20,1) -> 83 | Q25: =ROUND(P25*O25,1) -> 66.4 | R25: =IF(Q25>=70,"1 - Target now",IF(Q25>=55,"2 - Target next",IF(Q25>=40,"3 - Support only",IF(Q25>=28,"4 - Defer","5 - Do not chase organically")))) -> 2 - Target next | S25: [STRATEGIC-JUDGEMENT] | T25: Less contested than the Shopify equivalent
A26: woocommerce speed optimisation service | B26: Transactional | C26: UK | D26: /services/woocommerce-development/woocommerce-speed-optimisation/ | E26: Sub-service | F26: DATA REQUIRED | G26: DATA REQUIRED | H26: DATA REQUIRED | I26: [DATA REQUIRED - PAID TOOL] | J26: 5 | K26: 4 | L26: 2 | M26: 4 | N26: A | O26: =IFERROR(INDEX('07 Scoring Model'!$B$14:$B$17,MATCH(N26,'07 Scoring Model'!$A$14:$A$17,0)),0) -> 1 | P26: =ROUND((J26*'07 Scoring Model'!$B$5 + K26*'07 Scoring Model'!$B$6 + L26*'07 Scoring Model'!$B$7 + M26*'07 Scoring Model'!$B$8)*20,1) -> 79 | Q26: =ROUND(P26*O26,1) -> 79 | R26: =IF(Q26>=70,"1 - Target now",IF(Q26>=55,"2 - Target next",IF(Q26>=40,"3 - Support only",IF(Q26>=28,"4 - Defer","5 - Do not chase organically")))) -> 1 - Target now | S26: [STRATEGIC-JUDGEMENT]
A27: woocommerce to shopify migration | B27: Transactional | C27: AU | D27: /services/migrations/woocommerce-to-shopify/ | E27: Migration | F27: DATA REQUIRED | G27: DATA REQUIRED | H27: DATA REQUIRED | I27: [DATA REQUIRED - PAID TOOL] | J27: 5 | K27: 4 | L27: 3 | M27: 4 | N27: B | O27: =IFERROR(INDEX('07 Scoring Model'!$B$14:$B$17,MATCH(N27,'07 Scoring Model'!$A$14:$A$17,0)),0) -> 0.8 | P27: =ROUND((J27*'07 Scoring Model'!$B$5 + K27*'07 Scoring Model'!$B$6 + L27*'07 Scoring Model'!$B$7 + M27*'07 Scoring Model'!$B$8)*20,1) -> 83 | Q27: =ROUND(P27*O27,1) -> 66.4 | R27: =IF(Q27>=70,"1 - Target now",IF(Q27>=55,"2 - Target next",IF(Q27>=40,"3 - Support only",IF(Q27>=28,"4 - Defer","5 - Do not chase organically")))) -> 2 - Target next | S27: [VERIFIED-FILE] | T27: Competitor ranks a dedicated page for this exact pairing
A28: shopify to woocommerce migration | B28: Transactional | C28: US | D28: /services/migrations/shopify-to-woocommerce/ | E28: Migration | F28: DATA REQUIRED | G28: DATA REQUIRED | H28: DATA REQUIRED | I28: [DATA REQUIRED - PAID TOOL] | J28: 5 | K28: 3 | L28: 2 | M28: 3 | N28: A | O28: =IFERROR(INDEX('07 Scoring Model'!$B$14:$B$17,MATCH(N28,'07 Scoring Model'!$A$14:$A$17,0)),0) -> 1 | P28: =ROUND((J28*'07 Scoring Model'!$B$5 + K28*'07 Scoring Model'!$B$6 + L28*'07 Scoring Model'!$B$7 + M28*'07 Scoring Model'!$B$8)*20,1) -> 70 | Q28: =ROUND(P28*O28,1) -> 70 | R28: =IF(Q28>=70,"1 - Target now",IF(Q28>=55,"2 - Target next",IF(Q28>=40,"3 - Support only",IF(Q28>=28,"4 - Defer","5 - Do not chase organically")))) -> 1 - Target now | S28: [STRATEGIC-JUDGEMENT] | T28: Reverse direction is far less served
A29: woocommerce vs shopify for a growing store | B29: Commercial | C29: AU | D29: /insights/woocommerce-vs-shopify/ | E29: Insight | F29: DATA REQUIRED | G29: DATA REQUIRED | H29: DATA REQUIRED | I29: [DATA REQUIRED - PAID TOOL] | J29: 4 | K29: 4 | L29: 4 | M29: 4 | N29: B | O29: =IFERROR(INDEX('07 Scoring Model'!$B$14:$B$17,MATCH(N29,'07 Scoring Model'!$A$14:$A$17,0)),0) -> 0.8 | P29: =ROUND((J29*'07 Scoring Model'!$B$5 + K29*'07 Scoring Model'!$B$6 + L29*'07 Scoring Model'!$B$7 + M29*'07 Scoring Model'!$B$8)*20,1) -> 80 | Q29: =ROUND(P29*O29,1) -> 64 | R29: =IF(Q29>=70,"1 - Target now",IF(Q29>=55,"2 - Target next",IF(Q29>=40,"3 - Support only",IF(Q29>=28,"4 - Defer","5 - Do not chase organically")))) -> 2 - Target next | S29: [VERIFIED-FILE] | T29: Competitor has this; expect a strong incumbent
A30: shopify development agency | B30: Transactional | C30: AU | D30: /services/shopify-ecommerce/ | E30: Service | F30: DATA REQUIRED | G30: DATA REQUIRED | H30: DATA REQUIRED | I30: [DATA REQUIRED - PAID TOOL] | J30: 5 | K30: 5 | L30: 4 | M30: 5 | N30: D | O30: =IFERROR(INDEX('07 Scoring Model'!$B$14:$B$17,MATCH(N30,'07 Scoring Model'!$A$14:$A$17,0)),0) -> 0.25 | P30: =ROUND((J30*'07 Scoring Model'!$B$5 + K30*'07 Scoring Model'!$B$6 + L30*'07 Scoring Model'!$B$7 + M30*'07 Scoring Model'!$B$8)*20,1) -> 96 | Q30: =ROUND(P30*O30,1) -> 24 | R30: =IF(Q30>=70,"1 - Target now",IF(Q30>=55,"2 - Target next",IF(Q30>=40,"3 - Support only",IF(Q30>=28,"4 - Defer","5 - Do not chase organically")))) -> 5 - Do not chase organically | S30: [VERIFIED-FILE] | T30: GATED. Competitor and local agencies own this. Not a first-year target
A31: shopify development company | B31: Transactional | C31: US | D31: /services/shopify-ecommerce/ | E31: Service | F31: DATA REQUIRED | G31: DATA REQUIRED | H31: DATA REQUIRED | I31: [DATA REQUIRED - PAID TOOL] | J31: 5 | K31: 5 | L31: 4 | M31: 5 | N31: D | O31: =IFERROR(INDEX('07 Scoring Model'!$B$14:$B$17,MATCH(N31,'07 Scoring Model'!$A$14:$A$17,0)),0) -> 0.25 | P31: =ROUND((J31*'07 Scoring Model'!$B$5 + K31*'07 Scoring Model'!$B$6 + L31*'07 Scoring Model'!$B$7 + M31*'07 Scoring Model'!$B$8)*20,1) -> 96 | Q31: =ROUND(P31*O31,1) -> 24 | R31: =IF(Q31>=70,"1 - Target now",IF(Q31>=55,"2 - Target next",IF(Q31>=40,"3 - Support only",IF(Q31>=28,"4 - Defer","5 - Do not chase organically")))) -> 5 - Do not chase organically | S31: [STRATEGIC-JUDGEMENT] | T31: GATED. Same page as above
A32: shopify migration services | B32: Transactional | C32: UK | D32: /services/shopify-ecommerce/shopify-migration/ | E32: Sub-service | F32: DATA REQUIRED | G32: DATA REQUIRED | H32: DATA REQUIRED | I32: [DATA REQUIRED - PAID TOOL] | J32: 5 | K32: 4 | L32: 3 | M32: 4 | N32: C | O32: =IFERROR(INDEX('07 Scoring Model'!$B$14:$B$17,MATCH(N32,'07 Scoring Model'!$A$14:$A$17,0)),0) -> 0.55 | P32: =ROUND((J32*'07 Scoring Model'!$B$5 + K32*'07 Scoring Model'!$B$6 + L32*'07 Scoring Model'!$B$7 + M32*'07 Scoring Model'!$B$8)*20,1) -> 83 | Q32: =ROUND(P32*O32,1) -> 45.7 | R32: =IF(Q32>=70,"1 - Target now",IF(Q32>=55,"2 - Target next",IF(Q32>=40,"3 - Support only",IF(Q32>=28,"4 - Defer","5 - Do not chase organically")))) -> 3 - Support only | S32: [VERIFIED-FILE] | T32: GATED
A33: magento to shopify migration | B33: Transactional | C33: UK | D33: /services/migrations/magento-to-shopify/ | E33: Migration | F33: DATA REQUIRED | G33: DATA REQUIRED | H33: DATA REQUIRED | I33: [DATA REQUIRED - PAID TOOL] | J33: 5 | K33: 4 | L33: 3 | M33: 4 | N33: C | O33: =IFERROR(INDEX('07 Scoring Model'!$B$14:$B$17,MATCH(N33,'07 Scoring Model'!$A$14:$A$17,0)),0) -> 0.55 | P33: =ROUND((J33*'07 Scoring Model'!$B$5 + K33*'07 Scoring Model'!$B$6 + L33*'07 Scoring Model'!$B$7 + M33*'07 Scoring Model'!$B$8)*20,1) -> 83 | Q33: =ROUND(P33*O33,1) -> 45.7 | R33: =IF(Q33>=70,"1 - Target now",IF(Q33>=55,"2 - Target next",IF(Q33>=40,"3 - Support only",IF(Q33>=28,"4 - Defer","5 - Do not chase organically")))) -> 3 - Support only | S33: [VERIFIED-FILE] | T33: GATED. Competitor page is ~1,066 words
A34: shopify speed optimisation service | B34: Transactional | C34: US | D34: /services/shopify-ecommerce/shopify-speed-optimisation/ | E34: Sub-service | F34: DATA REQUIRED | G34: DATA REQUIRED | H34: DATA REQUIRED | I34: [DATA REQUIRED - PAID TOOL] | J34: 5 | K34: 4 | L34: 3 | M34: 4 | N34: B | O34: =IFERROR(INDEX('07 Scoring Model'!$B$14:$B$17,MATCH(N34,'07 Scoring Model'!$A$14:$A$17,0)),0) -> 0.8 | P34: =ROUND((J34*'07 Scoring Model'!$B$5 + K34*'07 Scoring Model'!$B$6 + L34*'07 Scoring Model'!$B$7 + M34*'07 Scoring Model'!$B$8)*20,1) -> 83 | Q34: =ROUND(P34*O34,1) -> 66.4 | R34: =IF(Q34>=70,"1 - Target now",IF(Q34>=55,"2 - Target next",IF(Q34>=40,"3 - Support only",IF(Q34>=28,"4 - Defer","5 - Do not chase organically")))) -> 2 - Target next | S34: [VERIFIED-FILE] | T34: GATED. Narrow technical problem, more winnable than the head term
A35: shopify seo services | B35: Transactional | C35: AU | D35: /services/seo/shopify-seo/ | E35: Sub-service | F35: DATA REQUIRED | G35: DATA REQUIRED | H35: DATA REQUIRED | I35: [DATA REQUIRED - PAID TOOL] | J35: 5 | K35: 4 | L35: 3 | M35: 4 | N35: C | O35: =IFERROR(INDEX('07 Scoring Model'!$B$14:$B$17,MATCH(N35,'07 Scoring Model'!$A$14:$A$17,0)),0) -> 0.55 | P35: =ROUND((J35*'07 Scoring Model'!$B$5 + K35*'07 Scoring Model'!$B$6 + L35*'07 Scoring Model'!$B$7 + M35*'07 Scoring Model'!$B$8)*20,1) -> 83 | Q35: =ROUND(P35*O35,1) -> 45.7 | R35: =IF(Q35>=70,"1 - Target now",IF(Q35>=55,"2 - Target next",IF(Q35>=40,"3 - Support only",IF(Q35>=28,"4 - Defer","5 - Do not chase organically")))) -> 3 - Support only | S35: [VERIFIED-FILE] | T35: GATED
A36: hire shopify developer | B36: Transactional | C36: US | D36: /services/dedicated-development-team/ | E36: Service | F36: DATA REQUIRED | G36: DATA REQUIRED | H36: DATA REQUIRED | I36: [DATA REQUIRED - PAID TOOL] | J36: 5 | K36: 4 | L36: 4 | M36: 4 | N36: C | O36: =IFERROR(INDEX('07 Scoring Model'!$B$14:$B$17,MATCH(N36,'07 Scoring Model'!$A$14:$A$17,0)),0) -> 0.55 | P36: =ROUND((J36*'07 Scoring Model'!$B$5 + K36*'07 Scoring Model'!$B$6 + L36*'07 Scoring Model'!$B$7 + M36*'07 Scoring Model'!$B$8)*20,1) -> 87 | Q36: =ROUND(P36*O36,1) -> 47.9 | R36: =IF(Q36>=70,"1 - Target now",IF(Q36>=55,"2 - Target next",IF(Q36>=40,"3 - Support only",IF(Q36>=28,"4 - Defer","5 - Do not chase organically")))) -> 3 - Support only | S36: [STRATEGIC-JUDGEMENT] | T36: GATED. Route to the dedicated-team page, not a new one
A37: shopify development cost | B37: Commercial | C37: US | D37: /insights/shopify-development-cost/ | E37: Insight | F37: DATA REQUIRED | G37: DATA REQUIRED | H37: DATA REQUIRED | I37: [DATA REQUIRED - PAID TOOL] | J37: 4 | K37: 4 | L37: 4 | M37: 4 | N37: B | O37: =IFERROR(INDEX('07 Scoring Model'!$B$14:$B$17,MATCH(N37,'07 Scoring Model'!$A$14:$A$17,0)),0) -> 0.8 | P37: =ROUND((J37*'07 Scoring Model'!$B$5 + K37*'07 Scoring Model'!$B$6 + L37*'07 Scoring Model'!$B$7 + M37*'07 Scoring Model'!$B$8)*20,1) -> 80 | Q37: =ROUND(P37*O37,1) -> 64 | R37: =IF(Q37>=70,"1 - Target now",IF(Q37>=55,"2 - Target next",IF(Q37>=40,"3 - Support only",IF(Q37>=28,"4 - Defer","5 - Do not chase organically")))) -> 2 - Target next | S37: [VERIFIED-FILE] | T37: GATED
A38: shopify xero integration | B38: Transactional | C38: AU | D38: /services/integrations/shopify-xero/ | E38: Integration | F38: DATA REQUIRED | G38: DATA REQUIRED | H38: DATA REQUIRED | I38: [DATA REQUIRED - PAID TOOL] | J38: 5 | K38: 4 | L38: 2 | M38: 4 | N38: B | O38: =IFERROR(INDEX('07 Scoring Model'!$B$14:$B$17,MATCH(N38,'07 Scoring Model'!$A$14:$A$17,0)),0) -> 0.8 | P38: =ROUND((J38*'07 Scoring Model'!$B$5 + K38*'07 Scoring Model'!$B$6 + L38*'07 Scoring Model'!$B$7 + M38*'07 Scoring Model'!$B$8)*20,1) -> 79 | Q38: =ROUND(P38*O38,1) -> 63.2 | R38: =IF(Q38>=70,"1 - Target now",IF(Q38>=55,"2 - Target next",IF(Q38>=40,"3 - Support only",IF(Q38>=28,"4 - Defer","5 - Do not chase organically")))) -> 2 - Target next | S38: [VERIFIED-FILE] | T38: GATED. Competitor page ~985 words
A39: wordpress hubspot integration | B39: Transactional | C39: US | D39: /services/integrations/wordpress-hubspot/ | E39: Integration | F39: DATA REQUIRED | G39: DATA REQUIRED | H39: DATA REQUIRED | I39: [DATA REQUIRED - PAID TOOL] | J39: 5 | K39: 4 | L39: 2 | M39: 4 | N39: A | O39: =IFERROR(INDEX('07 Scoring Model'!$B$14:$B$17,MATCH(N39,'07 Scoring Model'!$A$14:$A$17,0)),0) -> 1 | P39: =ROUND((J39*'07 Scoring Model'!$B$5 + K39*'07 Scoring Model'!$B$6 + L39*'07 Scoring Model'!$B$7 + M39*'07 Scoring Model'!$B$8)*20,1) -> 79 | Q39: =ROUND(P39*O39,1) -> 79 | R39: =IF(Q39>=70,"1 - Target now",IF(Q39>=55,"2 - Target next",IF(Q39>=40,"3 - Support only",IF(Q39>=28,"4 - Defer","5 - Do not chase organically")))) -> 1 - Target now | S39: [COMPETITOR-DERIVED] | T39: Pattern transferred to Hiver's real stack
A40: wordpress salesforce integration | B40: Transactional | C40: US | D40: /services/integrations/wordpress-salesforce/ | E40: Integration | F40: DATA REQUIRED | G40: DATA REQUIRED | H40: DATA REQUIRED | I40: [DATA REQUIRED - PAID TOOL] | J40: 5 | K40: 4 | L40: 2 | M40: 4 | N40: A | O40: =IFERROR(INDEX('07 Scoring Model'!$B$14:$B$17,MATCH(N40,'07 Scoring Model'!$A$14:$A$17,0)),0) -> 1 | P40: =ROUND((J40*'07 Scoring Model'!$B$5 + K40*'07 Scoring Model'!$B$6 + L40*'07 Scoring Model'!$B$7 + M40*'07 Scoring Model'!$B$8)*20,1) -> 79 | Q40: =ROUND(P40*O40,1) -> 79 | R40: =IF(Q40>=70,"1 - Target now",IF(Q40>=55,"2 - Target next",IF(Q40>=40,"3 - Support only",IF(Q40>=28,"4 - Defer","5 - Do not chase organically")))) -> 1 - Target now | S40: [COMPETITOR-DERIVED]
A41: crm erp integration services | B41: Transactional | C41: UK | D41: /services/integrations/crm-erp-integration/ | E41: Integration | F41: DATA REQUIRED | G41: DATA REQUIRED | H41: DATA REQUIRED | I41: [DATA REQUIRED - PAID TOOL] | J41: 5 | K41: 5 | L41: 2 | M41: 4 | N41: B | O41: =IFERROR(INDEX('07 Scoring Model'!$B$14:$B$17,MATCH(N41,'07 Scoring Model'!$A$14:$A$17,0)),0) -> 0.8 | P41: =ROUND((J41*'07 Scoring Model'!$B$5 + K41*'07 Scoring Model'!$B$6 + L41*'07 Scoring Model'!$B$7 + M41*'07 Scoring Model'!$B$8)*20,1) -> 85 | Q41: =ROUND(P41*O41,1) -> 68 | R41: =IF(Q41>=70,"1 - Target now",IF(Q41>=55,"2 - Target next",IF(Q41>=40,"3 - Support only",IF(Q41>=28,"4 - Defer","5 - Do not chase organically")))) -> 2 - Target next | S41: [STRATEGIC-JUDGEMENT] | T41: High deal value
A42: custom api integration development | B42: Transactional | C42: US | D42: /services/integrations/ | E42: Hub | F42: DATA REQUIRED | G42: DATA REQUIRED | H42: DATA REQUIRED | I42: [DATA REQUIRED - PAID TOOL] | J42: 5 | K42: 5 | L42: 3 | M42: 5 | N42: B | O42: =IFERROR(INDEX('07 Scoring Model'!$B$14:$B$17,MATCH(N42,'07 Scoring Model'!$A$14:$A$17,0)),0) -> 0.8 | P42: =ROUND((J42*'07 Scoring Model'!$B$5 + K42*'07 Scoring Model'!$B$6 + L42*'07 Scoring Model'!$B$7 + M42*'07 Scoring Model'!$B$8)*20,1) -> 92 | Q42: =ROUND(P42*O42,1) -> 73.6 | R42: =IF(Q42>=70,"1 - Target now",IF(Q42>=55,"2 - Target next",IF(Q42>=40,"3 - Support only",IF(Q42>=28,"4 - Defer","5 - Do not chase organically")))) -> 1 - Target now | S42: [STRATEGIC-JUDGEMENT]
A43: school management software api integration | B43: Transactional | C43: US | D43: /services/integrations/ | E43: Hub | F43: DATA REQUIRED | G43: DATA REQUIRED | H43: DATA REQUIRED | I43: [DATA REQUIRED - PAID TOOL] | J43: 4 | K43: 5 | L43: 1 | M43: 5 | N43: A | O43: =IFERROR(INDEX('07 Scoring Model'!$B$14:$B$17,MATCH(N43,'07 Scoring Model'!$A$14:$A$17,0)),0) -> 1 | P43: =ROUND((J43*'07 Scoring Model'!$B$5 + K43*'07 Scoring Model'!$B$6 + L43*'07 Scoring Model'!$B$7 + M43*'07 Scoring Model'!$B$8)*20,1) -> 77 | Q43: =ROUND(P43*O43,1) -> 77 | R43: =IF(Q43>=70,"1 - Target now",IF(Q43>=55,"2 - Target next",IF(Q43>=40,"3 - Support only",IF(Q43>=28,"4 - Defer","5 - Do not chase organically")))) -> 1 - Target now | S43: [VERIFIED-SITE] | T43: Ties the agency and product sides together
A44: technical seo agency | B44: Transactional | C44: UK | D44: /services/seo/technical-seo/ | E44: Sub-service | F44: DATA REQUIRED | G44: DATA REQUIRED | H44: DATA REQUIRED | I44: [DATA REQUIRED - PAID TOOL] | J44: 5 | K44: 4 | L44: 3 | M44: 4 | N44: C | O44: =IFERROR(INDEX('07 Scoring Model'!$B$14:$B$17,MATCH(N44,'07 Scoring Model'!$A$14:$A$17,0)),0) -> 0.55 | P44: =ROUND((J44*'07 Scoring Model'!$B$5 + K44*'07 Scoring Model'!$B$6 + L44*'07 Scoring Model'!$B$7 + M44*'07 Scoring Model'!$B$8)*20,1) -> 83 | Q44: =ROUND(P44*O44,1) -> 45.7 | R44: =IF(Q44>=70,"1 - Target now",IF(Q44>=55,"2 - Target next",IF(Q44>=40,"3 - Support only",IF(Q44>=28,"4 - Defer","5 - Do not chase organically")))) -> 3 - Support only | S44: [STRATEGIC-JUDGEMENT]
A45: ecommerce seo agency | B45: Transactional | C45: US | D45: /services/seo/ecommerce-seo/ | E45: Sub-service | F45: DATA REQUIRED | G45: DATA REQUIRED | H45: DATA REQUIRED | I45: [DATA REQUIRED - PAID TOOL] | J45: 5 | K45: 4 | L45: 3 | M45: 4 | N45: C | O45: =IFERROR(INDEX('07 Scoring Model'!$B$14:$B$17,MATCH(N45,'07 Scoring Model'!$A$14:$A$17,0)),0) -> 0.55 | P45: =ROUND((J45*'07 Scoring Model'!$B$5 + K45*'07 Scoring Model'!$B$6 + L45*'07 Scoring Model'!$B$7 + M45*'07 Scoring Model'!$B$8)*20,1) -> 83 | Q45: =ROUND(P45*O45,1) -> 45.7 | R45: =IF(Q45>=70,"1 - Target now",IF(Q45>=55,"2 - Target next",IF(Q45>=40,"3 - Support only",IF(Q45>=28,"4 - Defer","5 - Do not chase organically")))) -> 3 - Support only | S45: [STRATEGIC-JUDGEMENT]
A46: seo audit service | B46: Transactional | C46: AU | D46: /services/seo/seo-audit/ | E46: Sub-service | F46: DATA REQUIRED | G46: DATA REQUIRED | H46: DATA REQUIRED | I46: [DATA REQUIRED - PAID TOOL] | J46: 5 | K46: 4 | L46: 3 | M46: 4 | N46: B | O46: =IFERROR(INDEX('07 Scoring Model'!$B$14:$B$17,MATCH(N46,'07 Scoring Model'!$A$14:$A$17,0)),0) -> 0.8 | P46: =ROUND((J46*'07 Scoring Model'!$B$5 + K46*'07 Scoring Model'!$B$6 + L46*'07 Scoring Model'!$B$7 + M46*'07 Scoring Model'!$B$8)*20,1) -> 83 | Q46: =ROUND(P46*O46,1) -> 66.4 | R46: =IF(Q46>=70,"1 - Target now",IF(Q46>=55,"2 - Target next",IF(Q46>=40,"3 - Support only",IF(Q46>=28,"4 - Defer","5 - Do not chase organically")))) -> 2 - Target next | S46: [VERIFIED-FILE] | T46: Also the strongest lead-magnet offer
A47: wordpress seo services | B47: Transactional | C47: UK | D47: /services/seo/wordpress-seo/ | E47: Sub-service | F47: DATA REQUIRED | G47: DATA REQUIRED | H47: DATA REQUIRED | I47: [DATA REQUIRED - PAID TOOL] | J47: 5 | K47: 4 | L47: 3 | M47: 4 | N47: B | O47: =IFERROR(INDEX('07 Scoring Model'!$B$14:$B$17,MATCH(N47,'07 Scoring Model'!$A$14:$A$17,0)),0) -> 0.8 | P47: =ROUND((J47*'07 Scoring Model'!$B$5 + K47*'07 Scoring Model'!$B$6 + L47*'07 Scoring Model'!$B$7 + M47*'07 Scoring Model'!$B$8)*20,1) -> 83 | Q47: =ROUND(P47*O47,1) -> 66.4 | R47: =IF(Q47>=70,"1 - Target now",IF(Q47>=55,"2 - Target next",IF(Q47>=40,"3 - Support only",IF(Q47>=28,"4 - Defer","5 - Do not chase organically")))) -> 2 - Target next | S47: [STRATEGIC-JUDGEMENT]
A48: website migration seo checklist | B48: Informational | C48: US | D48: /insights/website-migration-seo-checklist/ | E48: Insight | F48: DATA REQUIRED | G48: DATA REQUIRED | H48: DATA REQUIRED | I48: [DATA REQUIRED - PAID TOOL] | J48: 3 | K48: 4 | L48: 3 | M48: 4 | N48: A | O48: =IFERROR(INDEX('07 Scoring Model'!$B$14:$B$17,MATCH(N48,'07 Scoring Model'!$A$14:$A$17,0)),0) -> 1 | P48: =ROUND((J48*'07 Scoring Model'!$B$5 + K48*'07 Scoring Model'!$B$6 + L48*'07 Scoring Model'!$B$7 + M48*'07 Scoring Model'!$B$8)*20,1) -> 69 | Q48: =ROUND(P48*O48,1) -> 69 | R48: =IF(Q48>=70,"1 - Target now",IF(Q48>=55,"2 - Target next",IF(Q48>=40,"3 - Support only",IF(Q48>=28,"4 - Defer","5 - Do not chase organically")))) -> 2 - Target next | S48: [VERIFIED-FILE] | T48: Hiver will run its own migration; write it from real experience
A49: marketing automation agency | B49: Transactional | C49: US | D49: /services/marketing-automation/ | E49: Service | F49: DATA REQUIRED | G49: DATA REQUIRED | H49: DATA REQUIRED | I49: [DATA REQUIRED - PAID TOOL] | J49: 5 | K49: 4 | L49: 3 | M49: 4 | N49: C | O49: =IFERROR(INDEX('07 Scoring Model'!$B$14:$B$17,MATCH(N49,'07 Scoring Model'!$A$14:$A$17,0)),0) -> 0.55 | P49: =ROUND((J49*'07 Scoring Model'!$B$5 + K49*'07 Scoring Model'!$B$6 + L49*'07 Scoring Model'!$B$7 + M49*'07 Scoring Model'!$B$8)*20,1) -> 83 | Q49: =ROUND(P49*O49,1) -> 45.7 | R49: =IF(Q49>=70,"1 - Target now",IF(Q49>=55,"2 - Target next",IF(Q49>=40,"3 - Support only",IF(Q49>=28,"4 - Defer","5 - Do not chase organically")))) -> 3 - Support only | S49: [STRATEGIC-JUDGEMENT]
A50: klaviyo email marketing agency | B50: Transactional | C50: AU | D50: /services/marketing-automation/klaviyo/ | E50: Sub-service | F50: DATA REQUIRED | G50: DATA REQUIRED | H50: DATA REQUIRED | I50: [DATA REQUIRED - PAID TOOL] | J50: 5 | K50: 3 | L50: 2 | M50: 3 | N50: C | O50: =IFERROR(INDEX('07 Scoring Model'!$B$14:$B$17,MATCH(N50,'07 Scoring Model'!$A$14:$A$17,0)),0) -> 0.55 | P50: =ROUND((J50*'07 Scoring Model'!$B$5 + K50*'07 Scoring Model'!$B$6 + L50*'07 Scoring Model'!$B$7 + M50*'07 Scoring Model'!$B$8)*20,1) -> 70 | Q50: =ROUND(P50*O50,1) -> 38.5 | R50: =IF(Q50>=70,"1 - Target now",IF(Q50>=55,"2 - Target next",IF(Q50>=40,"3 - Support only",IF(Q50>=28,"4 - Defer","5 - Do not chase organically")))) -> 4 - Defer | S50: [VERIFIED-FILE] | T50: GATED on real Klaviyo work
A51: lifecycle email marketing services | B51: Transactional | C51: UK | D51: /services/marketing-automation/ | E51: Service | F51: DATA REQUIRED | G51: DATA REQUIRED | H51: DATA REQUIRED | I51: [DATA REQUIRED - PAID TOOL] | J51: 5 | K51: 4 | L51: 2 | M51: 4 | N51: B | O51: =IFERROR(INDEX('07 Scoring Model'!$B$14:$B$17,MATCH(N51,'07 Scoring Model'!$A$14:$A$17,0)),0) -> 0.8 | P51: =ROUND((J51*'07 Scoring Model'!$B$5 + K51*'07 Scoring Model'!$B$6 + L51*'07 Scoring Model'!$B$7 + M51*'07 Scoring Model'!$B$8)*20,1) -> 79 | Q51: =ROUND(P51*O51,1) -> 63.2 | R51: =IF(Q51>=70,"1 - Target now",IF(Q51>=55,"2 - Target next",IF(Q51>=40,"3 - Support only",IF(Q51>=28,"4 - Defer","5 - Do not chase organically")))) -> 2 - Target next | S51: [STRATEGIC-JUDGEMENT] | T51: Consolidate welcome, nurture, win-back and cart recovery here
A52: abandoned cart automation setup | B52: Transactional | C52: US | D52: /services/marketing-automation/ | E52: Service | F52: DATA REQUIRED | G52: DATA REQUIRED | H52: DATA REQUIRED | I52: [DATA REQUIRED - PAID TOOL] | J52: 4 | K52: 3 | L52: 2 | M52: 3 | N52: A | O52: =IFERROR(INDEX('07 Scoring Model'!$B$14:$B$17,MATCH(N52,'07 Scoring Model'!$A$14:$A$17,0)),0) -> 1 | P52: =ROUND((J52*'07 Scoring Model'!$B$5 + K52*'07 Scoring Model'!$B$6 + L52*'07 Scoring Model'!$B$7 + M52*'07 Scoring Model'!$B$8)*20,1) -> 63 | Q52: =ROUND(P52*O52,1) -> 63 | R52: =IF(Q52>=70,"1 - Target now",IF(Q52>=55,"2 - Target next",IF(Q52>=40,"3 - Support only",IF(Q52>=28,"4 - Defer","5 - Do not chase organically")))) -> 2 - Target next | S52: [STRATEGIC-JUDGEMENT] | T52: Do not give this its own page
A53: crm follow up automation | B53: Transactional | C53: US | D53: /services/marketing-automation/ | E53: Service | F53: DATA REQUIRED | G53: DATA REQUIRED | H53: DATA REQUIRED | I53: [DATA REQUIRED - PAID TOOL] | J53: 4 | K53: 4 | L53: 2 | M53: 4 | N53: A | O53: =IFERROR(INDEX('07 Scoring Model'!$B$14:$B$17,MATCH(N53,'07 Scoring Model'!$A$14:$A$17,0)),0) -> 1 | P53: =ROUND((J53*'07 Scoring Model'!$B$5 + K53*'07 Scoring Model'!$B$6 + L53*'07 Scoring Model'!$B$7 + M53*'07 Scoring Model'!$B$8)*20,1) -> 72 | Q53: =ROUND(P53*O53,1) -> 72 | R53: =IF(Q53>=70,"1 - Target now",IF(Q53>=55,"2 - Target next",IF(Q53>=40,"3 - Support only",IF(Q53>=28,"4 - Defer","5 - Do not chase organically")))) -> 1 - Target now | S53: [STRATEGIC-JUDGEMENT] | T53: Consolidate; cannibalisation risk otherwise
A54: google ads management for ecommerce | B54: Transactional | C54: AU | D54: /services/digital-marketing/google-ads/ | E54: Sub-service | F54: DATA REQUIRED | G54: DATA REQUIRED | H54: DATA REQUIRED | I54: [DATA REQUIRED - PAID TOOL] | J54: 5 | K54: 3 | L54: 3 | M54: 3 | N54: C | O54: =IFERROR(INDEX('07 Scoring Model'!$B$14:$B$17,MATCH(N54,'07 Scoring Model'!$A$14:$A$17,0)),0) -> 0.55 | P54: =ROUND((J54*'07 Scoring Model'!$B$5 + K54*'07 Scoring Model'!$B$6 + L54*'07 Scoring Model'!$B$7 + M54*'07 Scoring Model'!$B$8)*20,1) -> 74 | Q54: =ROUND(P54*O54,1) -> 40.7 | R54: =IF(Q54>=70,"1 - Target now",IF(Q54>=55,"2 - Target next",IF(Q54>=40,"3 - Support only",IF(Q54>=28,"4 - Defer","5 - Do not chase organically")))) -> 3 - Support only | S54: [VERIFIED-FILE]
A55: meta ads agency | B55: Transactional | C55: US | D55: /services/digital-marketing/meta-ads/ | E55: Sub-service | F55: DATA REQUIRED | G55: DATA REQUIRED | H55: DATA REQUIRED | I55: [DATA REQUIRED - PAID TOOL] | J55: 5 | K55: 3 | L55: 3 | M55: 3 | N55: C | O55: =IFERROR(INDEX('07 Scoring Model'!$B$14:$B$17,MATCH(N55,'07 Scoring Model'!$A$14:$A$17,0)),0) -> 0.55 | P55: =ROUND((J55*'07 Scoring Model'!$B$5 + K55*'07 Scoring Model'!$B$6 + L55*'07 Scoring Model'!$B$7 + M55*'07 Scoring Model'!$B$8)*20,1) -> 74 | Q55: =ROUND(P55*O55,1) -> 40.7 | R55: =IF(Q55>=70,"1 - Target now",IF(Q55>=55,"2 - Target next",IF(Q55>=40,"3 - Support only",IF(Q55>=28,"4 - Defer","5 - Do not chase organically")))) -> 3 - Support only | S55: [STRATEGIC-JUDGEMENT]
A56: mobile app development company | B56: Transactional | C56: US | D56: /services/mobile-app-development/ | E56: Service | F56: DATA REQUIRED | G56: DATA REQUIRED | H56: DATA REQUIRED | I56: [DATA REQUIRED - PAID TOOL] | J56: 5 | K56: 4 | L56: 5 | M56: 4 | N56: D | O56: =IFERROR(INDEX('07 Scoring Model'!$B$14:$B$17,MATCH(N56,'07 Scoring Model'!$A$14:$A$17,0)),0) -> 0.25 | P56: =ROUND((J56*'07 Scoring Model'!$B$5 + K56*'07 Scoring Model'!$B$6 + L56*'07 Scoring Model'!$B$7 + M56*'07 Scoring Model'!$B$8)*20,1) -> 91 | Q56: =ROUND(P56*O56,1) -> 22.8 | R56: =IF(Q56>=70,"1 - Target now",IF(Q56>=55,"2 - Target next",IF(Q56>=40,"3 - Support only",IF(Q56>=28,"4 - Defer","5 - Do not chase organically")))) -> 5 - Do not chase organically | S56: [VERIFIED-SITE] | T56: Extremely contested; support page only
A57: react native app development company | B57: Transactional | C57: UK | D57: /services/mobile-app-development/ | E57: Service | F57: DATA REQUIRED | G57: DATA REQUIRED | H57: DATA REQUIRED | I57: [DATA REQUIRED - PAID TOOL] | J57: 5 | K57: 4 | L57: 3 | M57: 4 | N57: C | O57: =IFERROR(INDEX('07 Scoring Model'!$B$14:$B$17,MATCH(N57,'07 Scoring Model'!$A$14:$A$17,0)),0) -> 0.55 | P57: =ROUND((J57*'07 Scoring Model'!$B$5 + K57*'07 Scoring Model'!$B$6 + L57*'07 Scoring Model'!$B$7 + M57*'07 Scoring Model'!$B$8)*20,1) -> 83 | Q57: =ROUND(P57*O57,1) -> 45.7 | R57: =IF(Q57>=70,"1 - Target now",IF(Q57>=55,"2 - Target next",IF(Q57>=40,"3 - Support only",IF(Q57>=28,"4 - Defer","5 - Do not chase organically")))) -> 3 - Support only | S57: [STRATEGIC-JUDGEMENT]
A58: mobile app development cost | B58: Commercial | C58: AU | D58: /insights/mobile-app-development-cost/ | E58: Insight | F58: DATA REQUIRED | G58: DATA REQUIRED | H58: DATA REQUIRED | I58: [DATA REQUIRED - PAID TOOL] | J58: 4 | K58: 4 | L58: 4 | M58: 4 | N58: B | O58: =IFERROR(INDEX('07 Scoring Model'!$B$14:$B$17,MATCH(N58,'07 Scoring Model'!$A$14:$A$17,0)),0) -> 0.8 | P58: =ROUND((J58*'07 Scoring Model'!$B$5 + K58*'07 Scoring Model'!$B$6 + L58*'07 Scoring Model'!$B$7 + M58*'07 Scoring Model'!$B$8)*20,1) -> 80 | Q58: =ROUND(P58*O58,1) -> 64 | R58: =IF(Q58>=70,"1 - Target now",IF(Q58>=55,"2 - Target next",IF(Q58>=40,"3 - Support only",IF(Q58>=28,"4 - Defer","5 - Do not chase organically")))) -> 2 - Target next | S58: [STRATEGIC-JUDGEMENT]
A59: figma to webflow or wordpress handoff | B59: Commercial | C59: US | D59: /insights/figma-to-wordpress-handoff/ | E59: Insight | F59: DATA REQUIRED | G59: DATA REQUIRED | H59: DATA REQUIRED | I59: [DATA REQUIRED - PAID TOOL] | J59: 4 | K59: 3 | L59: 2 | M59: 3 | N59: A | O59: =IFERROR(INDEX('07 Scoring Model'!$B$14:$B$17,MATCH(N59,'07 Scoring Model'!$A$14:$A$17,0)),0) -> 1 | P59: =ROUND((J59*'07 Scoring Model'!$B$5 + K59*'07 Scoring Model'!$B$6 + L59*'07 Scoring Model'!$B$7 + M59*'07 Scoring Model'!$B$8)*20,1) -> 63 | Q59: =ROUND(P59*O59,1) -> 63 | R59: =IF(Q59>=70,"1 - Target now",IF(Q59>=55,"2 - Target next",IF(Q59>=40,"3 - Support only",IF(Q59>=28,"4 - Defer","5 - Do not chase organically")))) -> 2 - Target next | S59: [VERIFIED-SITE] | T59: Hiver lists Figma design as a live service
A60: ui ux design agency for saas | B60: Transactional | C60: US | D60: /services/ui-ux-design/ | E60: Service | F60: DATA REQUIRED | G60: DATA REQUIRED | H60: DATA REQUIRED | I60: [DATA REQUIRED - PAID TOOL] | J60: 5 | K60: 4 | L60: 3 | M60: 4 | N60: C | O60: =IFERROR(INDEX('07 Scoring Model'!$B$14:$B$17,MATCH(N60,'07 Scoring Model'!$A$14:$A$17,0)),0) -> 0.55 | P60: =ROUND((J60*'07 Scoring Model'!$B$5 + K60*'07 Scoring Model'!$B$6 + L60*'07 Scoring Model'!$B$7 + M60*'07 Scoring Model'!$B$8)*20,1) -> 83 | Q60: =ROUND(P60*O60,1) -> 45.7 | R60: =IF(Q60>=70,"1 - Target now",IF(Q60>=55,"2 - Target next",IF(Q60>=40,"3 - Support only",IF(Q60>=28,"4 - Defer","5 - Do not chase organically")))) -> 3 - Support only | S60: [STRATEGIC-JUDGEMENT]
A61: school management software | B61: Commercial | C61: US | D61: /products/school-management-software/ | E61: Product | F61: DATA REQUIRED | G61: DATA REQUIRED | H61: DATA REQUIRED | I61: [DATA REQUIRED - PAID TOOL] | J61: 4 | K61: 5 | L61: 5 | M61: 5 | N61: C | O61: =IFERROR(INDEX('07 Scoring Model'!$B$14:$B$17,MATCH(N61,'07 Scoring Model'!$A$14:$A$17,0)),0) -> 0.55 | P61: =ROUND((J61*'07 Scoring Model'!$B$5 + K61*'07 Scoring Model'!$B$6 + L61*'07 Scoring Model'!$B$7 + M61*'07 Scoring Model'!$B$8)*20,1) -> 93 | Q61: =ROUND(P61*O61,1) -> 51.2 | R61: =IF(Q61>=70,"1 - Target now",IF(Q61>=55,"2 - Target next",IF(Q61>=40,"3 - Support only",IF(Q61>=28,"4 - Defer","5 - Do not chase organically")))) -> 3 - Support only | S61: [VERIFIED-SITE] | T61: Product-category search; confirm product status first
A62: school management system for private schools | B62: Commercial | C62: UK | D62: /products/school-management-software/ | E62: Product | F62: DATA REQUIRED | G62: DATA REQUIRED | H62: DATA REQUIRED | I62: [DATA REQUIRED - PAID TOOL] | J62: 4 | K62: 5 | L62: 3 | M62: 5 | N62: B | O62: =IFERROR(INDEX('07 Scoring Model'!$B$14:$B$17,MATCH(N62,'07 Scoring Model'!$A$14:$A$17,0)),0) -> 0.8 | P62: =ROUND((J62*'07 Scoring Model'!$B$5 + K62*'07 Scoring Model'!$B$6 + L62*'07 Scoring Model'!$B$7 + M62*'07 Scoring Model'!$B$8)*20,1) -> 85 | Q62: =ROUND(P62*O62,1) -> 68 | R62: =IF(Q62>=70,"1 - Target now",IF(Q62>=55,"2 - Target next",IF(Q62>=40,"3 - Support only",IF(Q62>=28,"4 - Defer","5 - Do not chase organically")))) -> 2 - Target next | S62: [STRATEGIC-JUDGEMENT]
A63: dental practice management software | B63: Commercial | C63: AU | D63: /products/dental-practice-management-software/ | E63: Product | F63: DATA REQUIRED | G63: DATA REQUIRED | H63: DATA REQUIRED | I63: [DATA REQUIRED - PAID TOOL] | J63: 5 | K63: 5 | L63: 4 | M63: 5 | N63: C | O63: =IFERROR(INDEX('07 Scoring Model'!$B$14:$B$17,MATCH(N63,'07 Scoring Model'!$A$14:$A$17,0)),0) -> 0.55 | P63: =ROUND((J63*'07 Scoring Model'!$B$5 + K63*'07 Scoring Model'!$B$6 + L63*'07 Scoring Model'!$B$7 + M63*'07 Scoring Model'!$B$8)*20,1) -> 96 | Q63: =ROUND(P63*O63,1) -> 52.8 | R63: =IF(Q63>=70,"1 - Target now",IF(Q63>=55,"2 - Target next",IF(Q63>=40,"3 - Support only",IF(Q63>=28,"4 - Defer","5 - Do not chase organically")))) -> 3 - Support only | S63: [VERIFIED-SITE] | T63: Regulated category; check compliance claims carefully
A64: clinic management software | B64: Commercial | C64: US | D64: /products/clinic-management-software/ | E64: Product | F64: DATA REQUIRED | G64: DATA REQUIRED | H64: DATA REQUIRED | I64: [DATA REQUIRED - PAID TOOL] | J64: 5 | K64: 5 | L64: 4 | M64: 5 | N64: C | O64: =IFERROR(INDEX('07 Scoring Model'!$B$14:$B$17,MATCH(N64,'07 Scoring Model'!$A$14:$A$17,0)),0) -> 0.55 | P64: =ROUND((J64*'07 Scoring Model'!$B$5 + K64*'07 Scoring Model'!$B$6 + L64*'07 Scoring Model'!$B$7 + M64*'07 Scoring Model'!$B$8)*20,1) -> 96 | Q64: =ROUND(P64*O64,1) -> 52.8 | R64: =IF(Q64>=70,"1 - Target now",IF(Q64>=55,"2 - Target next",IF(Q64>=40,"3 - Support only",IF(Q64>=28,"4 - Defer","5 - Do not chase organically")))) -> 3 - Support only | S64: [VERIFIED-SITE]
A65: hr software for small business | B65: Commercial | C65: AU | D65: /products/hr-software/ | E65: Product | F65: DATA REQUIRED | G65: DATA REQUIRED | H65: DATA REQUIRED | I65: [DATA REQUIRED - PAID TOOL] | J65: 5 | K65: 4 | L65: 4 | M65: 4 | N65: C | O65: =IFERROR(INDEX('07 Scoring Model'!$B$14:$B$17,MATCH(N65,'07 Scoring Model'!$A$14:$A$17,0)),0) -> 0.55 | P65: =ROUND((J65*'07 Scoring Model'!$B$5 + K65*'07 Scoring Model'!$B$6 + L65*'07 Scoring Model'!$B$7 + M65*'07 Scoring Model'!$B$8)*20,1) -> 87 | Q65: =ROUND(P65*O65,1) -> 47.9 | R65: =IF(Q65>=70,"1 - Target now",IF(Q65>=55,"2 - Target next",IF(Q65>=40,"3 - Support only",IF(Q65>=28,"4 - Defer","5 - Do not chase organically")))) -> 3 - Support only | S65: [VERIFIED-SITE]
A66: employee management system | B66: Commercial | C66: US | D66: /products/employee-management-software/ | E66: Product | F66: DATA REQUIRED | G66: DATA REQUIRED | H66: DATA REQUIRED | I66: [DATA REQUIRED - PAID TOOL] | J66: 4 | K66: 4 | L66: 4 | M66: 4 | N66: C | O66: =IFERROR(INDEX('07 Scoring Model'!$B$14:$B$17,MATCH(N66,'07 Scoring Model'!$A$14:$A$17,0)),0) -> 0.55 | P66: =ROUND((J66*'07 Scoring Model'!$B$5 + K66*'07 Scoring Model'!$B$6 + L66*'07 Scoring Model'!$B$7 + M66*'07 Scoring Model'!$B$8)*20,1) -> 80 | Q66: =ROUND(P66*O66,1) -> 44 | R66: =IF(Q66>=70,"1 - Target now",IF(Q66>=55,"2 - Target next",IF(Q66>=40,"3 - Support only",IF(Q66>=28,"4 - Defer","5 - Do not chase organically")))) -> 3 - Support only | S66: [VERIFIED-SITE] | T66: Check overlap with HR software before building both
A67: custom school management software development | B67: Transactional | C67: US | D67: /products/school-management-software/ | E67: Product | F67: DATA REQUIRED | G67: DATA REQUIRED | H67: DATA REQUIRED | I67: [DATA REQUIRED - PAID TOOL] | J67: 5 | K67: 5 | L67: 2 | M67: 5 | N67: A | O67: =IFERROR(INDEX('07 Scoring Model'!$B$14:$B$17,MATCH(N67,'07 Scoring Model'!$A$14:$A$17,0)),0) -> 1 | P67: =ROUND((J67*'07 Scoring Model'!$B$5 + K67*'07 Scoring Model'!$B$6 + L67*'07 Scoring Model'!$B$7 + M67*'07 Scoring Model'!$B$8)*20,1) -> 88 | Q67: =ROUND(P67*O67,1) -> 88 | R67: =IF(Q67>=70,"1 - Target now",IF(Q67>=55,"2 - Target next",IF(Q67>=40,"3 - Support only",IF(Q67>=28,"4 - Defer","5 - Do not chase organically")))) -> 1 - Target now | S67: [STRATEGIC-JUDGEMENT] | T67: Bridges product and services; strongest single opportunity in this set
A68: web development for healthcare providers | B68: Transactional | C68: US | D68: /industries/healthcare/ | E68: Industry | F68: DATA REQUIRED | G68: DATA REQUIRED | H68: DATA REQUIRED | I68: [DATA REQUIRED - PAID TOOL] | J68: 5 | K68: 4 | L68: 2 | M68: 4 | N68: B | O68: =IFERROR(INDEX('07 Scoring Model'!$B$14:$B$17,MATCH(N68,'07 Scoring Model'!$A$14:$A$17,0)),0) -> 0.8 | P68: =ROUND((J68*'07 Scoring Model'!$B$5 + K68*'07 Scoring Model'!$B$6 + L68*'07 Scoring Model'!$B$7 + M68*'07 Scoring Model'!$B$8)*20,1) -> 79 | Q68: =ROUND(P68*O68,1) -> 63.2 | R68: =IF(Q68>=70,"1 - Target now",IF(Q68>=55,"2 - Target next",IF(Q68>=40,"3 - Support only",IF(Q68>=28,"4 - Defer","5 - Do not chase organically")))) -> 2 - Target next | S68: [VERIFIED-SITE] | T68: Only build with a real healthcare case study
A69: education website development | B69: Transactional | C69: UK | D69: /industries/education/ | E69: Industry | F69: DATA REQUIRED | G69: DATA REQUIRED | H69: DATA REQUIRED | I69: [DATA REQUIRED - PAID TOOL] | J69: 4 | K69: 4 | L69: 2 | M69: 4 | N69: B | O69: =IFERROR(INDEX('07 Scoring Model'!$B$14:$B$17,MATCH(N69,'07 Scoring Model'!$A$14:$A$17,0)),0) -> 0.8 | P69: =ROUND((J69*'07 Scoring Model'!$B$5 + K69*'07 Scoring Model'!$B$6 + L69*'07 Scoring Model'!$B$7 + M69*'07 Scoring Model'!$B$8)*20,1) -> 72 | Q69: =ROUND(P69*O69,1) -> 57.6 | R69: =IF(Q69>=70,"1 - Target now",IF(Q69>=55,"2 - Target next",IF(Q69>=40,"3 - Support only",IF(Q69>=28,"4 - Defer","5 - Do not chase organically")))) -> 2 - Target next | S69: [VERIFIED-SITE] | T69: Anchor to the school-management product
A70: ecommerce website development services | B70: Transactional | C70: AU | D70: /industries/ecommerce/ | E70: Industry | F70: DATA REQUIRED | G70: DATA REQUIRED | H70: DATA REQUIRED | I70: [DATA REQUIRED - PAID TOOL] | J70: 5 | K70: 4 | L70: 4 | M70: 4 | N70: C | O70: =IFERROR(INDEX('07 Scoring Model'!$B$14:$B$17,MATCH(N70,'07 Scoring Model'!$A$14:$A$17,0)),0) -> 0.55 | P70: =ROUND((J70*'07 Scoring Model'!$B$5 + K70*'07 Scoring Model'!$B$6 + L70*'07 Scoring Model'!$B$7 + M70*'07 Scoring Model'!$B$8)*20,1) -> 87 | Q70: =ROUND(P70*O70,1) -> 47.9 | R70: =IF(Q70>=70,"1 - Target now",IF(Q70>=55,"2 - Target next",IF(Q70>=40,"3 - Support only",IF(Q70>=28,"4 - Defer","5 - Do not chase organically")))) -> 3 - Support only | S70: [STRATEGIC-JUDGEMENT]
A71: hiver technology | B71: Navigational | C71: Global | D71: / | E71: Home | F71: DATA REQUIRED | G71: DATA REQUIRED | H71: DATA REQUIRED | I71: [DATA REQUIRED - PAID TOOL] | J71: 3 | K71: 5 | L71: 1 | M71: 5 | N71: A | O71: =IFERROR(INDEX('07 Scoring Model'!$B$14:$B$17,MATCH(N71,'07 Scoring Model'!$A$14:$A$17,0)),0) -> 1 | P71: =ROUND((J71*'07 Scoring Model'!$B$5 + K71*'07 Scoring Model'!$B$6 + L71*'07 Scoring Model'!$B$7 + M71*'07 Scoring Model'!$B$8)*20,1) -> 70 | Q71: =ROUND(P71*O71,1) -> 70 | R71: =IF(Q71>=70,"1 - Target now",IF(Q71>=55,"2 - Target next",IF(Q71>=40,"3 - Support only",IF(Q71>=28,"4 - Defer","5 - Do not chase organically")))) -> 1 - Target now | S71: [VERIFIED-SITE] | T71: The only viable brand target; 'Hiver' alone is unwinnable
A72: hiver technology nepal | B72: Navigational | C72: Global | D72: /about/ | E72: About | F72: DATA REQUIRED | G72: DATA REQUIRED | H72: DATA REQUIRED | I72: [DATA REQUIRED - PAID TOOL] | J72: 3 | K72: 4 | L72: 1 | M72: 4 | N72: A | O72: =IFERROR(INDEX('07 Scoring Model'!$B$14:$B$17,MATCH(N72,'07 Scoring Model'!$A$14:$A$17,0)),0) -> 1 | P72: =ROUND((J72*'07 Scoring Model'!$B$5 + K72*'07 Scoring Model'!$B$6 + L72*'07 Scoring Model'!$B$7 + M72*'07 Scoring Model'!$B$8)*20,1) -> 61 | Q72: =ROUND(P72*O72,1) -> 61 | R72: =IF(Q72>=70,"1 - Target now",IF(Q72>=55,"2 - Target next",IF(Q72>=40,"3 - Support only",IF(Q72>=28,"4 - Defer","5 - Do not chase organically")))) -> 2 - Target next | S72: [VERIFIED-SITE]
A73: hiver technology reviews | B73: Navigational | C73: Global | D73: /about/ | E73: About | F73: DATA REQUIRED | G73: DATA REQUIRED | H73: DATA REQUIRED | I73: [DATA REQUIRED - PAID TOOL] | J73: 4 | K73: 4 | L73: 1 | M73: 5 | N73: B | O73: =IFERROR(INDEX('07 Scoring Model'!$B$14:$B$17,MATCH(N73,'07 Scoring Model'!$A$14:$A$17,0)),0) -> 0.8 | P73: =ROUND((J73*'07 Scoring Model'!$B$5 + K73*'07 Scoring Model'!$B$6 + L73*'07 Scoring Model'!$B$7 + M73*'07 Scoring Model'!$B$8)*20,1) -> 71 | Q73: =ROUND(P73*O73,1) -> 56.8 | R73: =IF(Q73>=70,"1 - Target now",IF(Q73>=55,"2 - Target next",IF(Q73>=40,"3 - Support only",IF(Q73>=28,"4 - Defer","5 - Do not chase organically")))) -> 2 - Target next | S73: [STRATEGIC-JUDGEMENT] | T73: Will be won by Clutch/G2 profiles, not by Hiver's own site
A75: Summary (formula-driven)
A76: Total keywords mapped | B76: =COUNTA(A4:A73) -> 70
A77: Tier A - target now | B77: =COUNTIF(N4:N73,"A") -> 22
A78: Tier B | B78: =COUNTIF(N4:N73,"B") -> 22
A79: Tier C | B79: =COUNTIF(N4:N73,"C") -> 23
A80: Tier D - not an organic bet | B80: =COUNTIF(N4:N73,"D") -> 3
A81: Transactional intent | B81: =COUNTIF(B4:B73,"Transactional") -> 48
A82: Commercial intent | B82: =COUNTIF(B4:B73,"Commercial") -> 16
A83: US targets | B83: =COUNTIF(C4:C73,"US") -> 36
A84: UK targets | B84: =COUNTIF(C4:C73,"UK") -> 16
A85: AU targets | B85: =COUNTIF(C4:C73,"AU") -> 15
A86: Keywords banded 'Target now' | B86: =COUNTIF(R4:R73,"1 - Target now") -> 20
A87: Keywords banded 'Do not chase organically' | B87: =COUNTIF(R4:R73,"5 - Do not chase organically") -> 3
A88: Average priority score | B88: =ROUND(AVERAGE(Q4:Q73),1) -> 60.5
A89: Highest priority score | B89: =ROUND(MAX(Q4:Q73),1) -> 92

Sheet 09 URL Map
A1: Site architecture and URL map
A2: Capability column gates publication. GATED and DATA REQUIRED rows must not go live until Hiver confirms the capability.
A3: URL | B3: Parent | C3: Page type | D3: Priority | E3: Primary keyword | F3: Intent | G3: Country | H3: Tier | I3: Capability | J3: Build status | K3: Note
A4: / | B4: - | C4: Home | D4: P0 | E4: hiver technology | F4: Navigational | G4: Global | H4: A | I4: Confirmed | J4: Rebuild | K4: Rewrite title and H1 around what Hiver actually does and for whom
A5: /services/ | B5: / | C5: Hub | D5: P0 | E5: software development services | F5: Commercial | G5: Global | H5: C | I5: Confirmed | J5: Build | K5: Real hub with 150+ words of orientation per child, not a link grid
A6: /services/web-application-development/ | B6: /services/ | C6: Service | D6: P0 | E6: custom web application development | F6: Transactional | G6: US | H6: C | I6: Confirmed | J6: Build | K6: Flagship page. Target 1,400-1,600 words per the competitor depth benchmark
A7: /services/crm-development/ | B7: /services/ | C7: Service | D7: P0 | E7: custom crm development | F7: Transactional | G7: US | H7: B | I7: Confirmed | J7: Build | K7: Already a live listed service; highest deal value of the confirmed set
A8: /services/wordpress-development/ | B8: /services/ | C8: Service | D8: P0 | E8: wordpress development company | F8: Transactional | G8: US | H8: C | I8: Confirmed | J8: Build
A9: /services/wordpress-development/headless-wordpress/ | B9: /services/wordpress-development/ | C9: Sub-service | D9: P2 | E9: headless wordpress development | F9: Transactional | G9: US | H9: B | I9: DATA REQUIRED | J9: Build | K9: Only if Hiver has shipped a headless build
A10: /services/wordpress-development/elementor-to-custom-theme/ | B10: /services/wordpress-development/ | C10: Sub-service | D10: P1 | E10: elementor to custom theme migration | F10: Transactional | G10: US | H10: A | I10: Confirmed | J10: Build | K10: Hiver can write this from its own migration experience
A11: /services/wordpress-maintenance/ | B11: /services/ | C11: Service | D11: P1 | E11: wordpress maintenance and support plans | F11: Transactional | G11: AU | H11: A | I11: Confirmed | J11: Build | K11: Retainer revenue; needs real plan tiers and pricing
A12: /services/wordpress-performance-optimisation/ | B12: /services/ | C12: Service | D12: P1 | E12: wordpress core web vitals fix | F12: Commercial | G12: UK | H12: A | I12: Confirmed | J12: Build | K12: Problem-led page; requires before/after evidence
A13: /services/mobile-app-development/ | B13: /services/ | C13: Service | D13: P0 | E13: mobile app development company | F13: Transactional | G13: US | H13: D | I13: Confirmed | J13: Build | K13: Needed for completeness; do not expect it to rank on the head term
A14: /services/ui-ux-design/ | B14: /services/ | C14: Service | D14: P1 | E14: ui ux design agency for saas | F14: Transactional | G14: US | H14: C | I14: Confirmed | J14: Build | K14: Merge the Figma offering into this page
A15: /services/dedicated-development-team/ | B15: /services/ | C15: Service | D15: P0 | E15: hire dedicated development team | F15: Transactional | G15: US | H15: B | I15: Confirmed | J15: Build | K15: The one page where Hiver's structure is an advantage. Handle the offshore objection head-on
A16: /services/woocommerce-development/ | B16: /services/ | C16: Service | D16: P1 | E16: woocommerce development agency | F16: Transactional | G16: UK | H16: B | I16: DATA REQUIRED | J16: Build | K16: Less contested than Shopify and closer to Hiver's WordPress base
A17: /services/woocommerce-development/woocommerce-speed-optimisation/ | B17: /services/woocommerce-development/ | C17: Sub-service | D17: P2 | E17: woocommerce speed optimisation service | F17: Transactional | G17: UK | H17: A | I17: DATA REQUIRED | J17: Build
A18: /services/shopify-ecommerce/ | B18: /services/ | C18: Service | D18: P1 | E18: shopify development agency | F18: Transactional | G18: AU | H18: D | I18: GATED | J18: Blocked | K18: Do not publish until Hiver confirms delivered Shopify stores and Partner status
A19: /services/shopify-ecommerce/shopify-store-development/ | B19: /services/shopify-ecommerce/ | C19: Sub-service | D19: P2 | E19: shopify store development | F19: Transactional | G19: US | H19: C | I19: GATED | J19: Blocked
A20: /services/shopify-ecommerce/shopify-migration/ | B20: /services/shopify-ecommerce/ | C20: Sub-service | D20: P2 | E20: shopify migration services | F20: Transactional | G20: UK | H20: C | I20: GATED | J20: Blocked
A21: /services/shopify-ecommerce/shopify-speed-optimisation/ | B21: /services/shopify-ecommerce/ | C21: Sub-service | D21: P2 | E21: shopify speed optimisation service | F21: Transactional | G21: US | H21: B | I21: GATED | J21: Blocked | K21: Most winnable of the Shopify set because the problem is narrow
A22: /services/seo/ | B22: /services/ | C22: Hub | D22: P1 | E22: seo services | F22: Commercial | G22: Global | H22: D | I22: DATA REQUIRED | J22: Build | K22: Hiver must be able to point at its own ranking site before selling SEO
A23: /services/seo/technical-seo/ | B23: /services/seo/ | C23: Sub-service | D23: P1 | E23: technical seo agency | F23: Transactional | G23: UK | H23: C | I23: DATA REQUIRED | J23: Build
A24: /services/seo/ecommerce-seo/ | B24: /services/seo/ | C24: Sub-service | D24: P2 | E24: ecommerce seo agency | F24: Transactional | G24: US | H24: C | I24: DATA REQUIRED | J24: Build
A25: /services/seo/wordpress-seo/ | B25: /services/seo/ | C25: Sub-service | D25: P2 | E25: wordpress seo services | F25: Transactional | G25: UK | H25: B | I25: DATA REQUIRED | J25: Build
A26: /services/seo/seo-audit/ | B26: /services/seo/ | C26: Sub-service | D26: P1 | E26: seo audit service | F26: Transactional | G26: AU | H26: B | I26: DATA REQUIRED | J26: Build | K26: Doubles as the primary lead magnet
A27: /services/seo/shopify-seo/ | B27: /services/seo/ | C27: Sub-service | D27: P3 | E27: shopify seo services | F27: Transactional | G27: AU | H27: C | I27: GATED | J27: Blocked
A28: /services/digital-marketing/ | B28: /services/ | C28: Hub | D28: P1 | E28: digital marketing agency | F28: Transactional | G28: US | H28: D | I28: Confirmed | J28: Build
A29: /services/digital-marketing/google-ads/ | B29: /services/digital-marketing/ | C29: Sub-service | D29: P2 | E29: google ads management for ecommerce | F29: Transactional | G29: AU | H29: C | I29: DATA REQUIRED | J29: Build
A30: /services/digital-marketing/meta-ads/ | B30: /services/digital-marketing/ | C30: Sub-service | D30: P2 | E30: meta ads agency | F30: Transactional | G30: US | H30: C | I30: Confirmed | J30: Build
A31: /services/marketing-automation/ | B31: /services/ | C31: Service | D31: P1 | E31: lifecycle email marketing services | F31: Transactional | G31: UK | H31: B | I31: Confirmed | J31: Build | K31: CONSOLIDATION: absorbs email marketing, newsletters, welcome sequences, win-back, cart recovery, lead nurture and CRM follow-up. Seven briefed pages become one
A32: /services/marketing-automation/klaviyo/ | B32: /services/marketing-automation/ | C32: Sub-service | D32: P3 | E32: klaviyo email marketing agency | F32: Transactional | G32: AU | H32: C | I32: GATED | J32: Blocked
A33: /services/integrations/ | B33: /services/ | C33: Hub | D33: P1 | E33: custom api integration development | F33: Transactional | G33: US | H33: B | I33: Confirmed | J33: Build | K33: Hub for the highest-yield long-tail pattern in the competitor dataset
A34: /services/integrations/wordpress-hubspot/ | B34: /services/integrations/ | C34: Integration | D34: P2 | E34: wordpress hubspot integration | F34: Transactional | G34: US | H34: A | I34: DATA REQUIRED | J34: Build | K34: Target ~950 words, 8-9 H2s, following the observed integration template
A35: /services/integrations/wordpress-salesforce/ | B35: /services/integrations/ | C35: Integration | D35: P2 | E35: wordpress salesforce integration | F35: Transactional | G35: US | H35: A | I35: DATA REQUIRED | J35: Build
A36: /services/integrations/crm-erp-integration/ | B36: /services/integrations/ | C36: Integration | D36: P2 | E36: crm erp integration services | F36: Transactional | G36: UK | H36: B | I36: DATA REQUIRED | J36: Build
A37: /services/migrations/ | B37: /services/ | C37: Hub | D37: P2 | E37: website migration services | F37: Transactional | G37: Global | H37: C | I37: Confirmed | J37: Build
A38: /services/migrations/woocommerce-to-shopify/ | B38: /services/migrations/ | C38: Migration | D38: P2 | E38: woocommerce to shopify migration | F38: Transactional | G38: AU | H38: B | I38: GATED | J38: Blocked
A39: /services/migrations/shopify-to-woocommerce/ | B39: /services/migrations/ | C39: Migration | D39: P2 | E39: shopify to woocommerce migration | F39: Transactional | G39: US | H39: A | I39: DATA REQUIRED | J39: Build | K39: Reverse direction is far less served than the forward one
A40: /products/ | B40: / | C40: Hub | D40: P1 | E40: business management software | F40: Commercial | G40: Global | H40: C | I40: DATA REQUIRED | J40: Build | K40: Confirm whether these are licensable products or bespoke builds before publishing
A41: /products/school-management-software/ | B41: /products/ | C41: Product | D41: P1 | E41: school management software | F41: Commercial | G41: US | H41: C | I41: DATA REQUIRED | J41: Build | K41: Strongest single opportunity outside the agency positioning
A42: /products/clinic-management-software/ | B42: /products/ | C42: Product | D42: P2 | E42: clinic management software | F42: Commercial | G42: US | H42: C | I42: DATA REQUIRED | J42: Build
A43: /products/dental-practice-management-software/ | B43: /products/ | C43: Product | D43: P2 | E43: dental practice management software | F43: Commercial | G43: AU | H43: C | I43: DATA REQUIRED | J43: Build | K43: Regulated category. Do not make clinical or compliance claims without evidence
A44: /products/hr-software/ | B44: /products/ | C44: Product | D44: P2 | E44: hr software for small business | F44: Commercial | G44: AU | H44: C | I44: DATA REQUIRED | J44: Build | K44: Check overlap with employee management before building both
A45: /industries/ | B45: / | C45: Hub | D45: P2 | E45: - | F45: - | G45: Global | H45: - | I45: Confirmed | J45: Build | K45: Only build the hub if at least two children are justified
A46: /industries/education/ | B46: /industries/ | C46: Industry | D46: P2 | E46: education website development | F46: Transactional | G46: UK | H46: B | I46: DATA REQUIRED | J46: Build | K46: Anchor to the school-management product
A47: /industries/healthcare/ | B47: /industries/ | C47: Industry | D47: P2 | E47: web development for healthcare providers | F47: Transactional | G47: US | H47: B | I47: DATA REQUIRED | J47: Build | K47: Requires a real healthcare project
A48: /industries/ecommerce/ | B48: /industries/ | C48: Industry | D48: P3 | E48: ecommerce website development services | F48: Transactional | G48: AU | H48: C | I48: GATED | J48: Blocked
A49: Travel / Banking / Logistics / Manufacturing / Government / Hotels / Construction | B49: /industries/ | C49: Industry | D49: DROP | E49: - | F49: - | G49: - | H49: - | I49: - | J49: Do not build | K49: No demand evidence, no case study, no distinct buyer problem. Building these creates thin pages. Revisit only with a real project
A50: /works/ | B50: / | C50: Hub | D50: P0 | E50: - | F50: - | G50: Global | H50: - | I50: Confirmed | J50: Build | K50: Replaces /portfolio/ with a 301
A51: /works/{project-slug}/ | B51: /works/ | C51: Case study | D51: P0 | E51: - | F51: - | G51: Global | H51: - | I51: DATA REQUIRED | J51: Blocked | K51: HARD BLOCKER. Needs a permissioned client, verified metrics and a testimonial. Beat the competitor's ~400-word depth
A52: /insights/ | B52: / | C52: Hub | D52: P0 | E52: - | F52: - | G52: Global | H52: - | I52: Confirmed | J52: Build | K52: Existing root-level posts must 301 in here
A53: /insights/{article-slug}/ | B53: /insights/ | C53: Insight | D53: P1 | E53: see Content Calendar | F53: Informational | G53: Various | H53: A | I53: Confirmed | J53: Build | K53: Target ~1,600-1,900 words to match the competitor's median
A54: /about/ | B54: / | C54: About | D54: P0 | E54: hiver technology | F54: Navigational | G54: Global | H54: A | I54: Confirmed | J54: Build | K54: Answer the offshore trust question directly and honestly
A55: /about/how-we-work/ | B55: /about/ | C55: Trust | D55: P1 | E55: - | F55: - | G55: Global | H55: - | I55: Confirmed | J55: Build | K55: Process, communication, timezone overlap, escalation, reporting
A56: /about/security-and-compliance/ | B56: /about/ | C56: Trust | D56: P1 | E56: - | F56: - | G56: Global | H56: - | I56: DATA REQUIRED | J56: Build | K56: NDA process, IP assignment, GDPR/DPA position, data residency, access control. Required for UK/EU buyers
A57: /about/pricing/ | B57: /about/ | C57: Trust | D57: P1 | E57: - | F57: - | G57: Global | H57: - | I57: DATA REQUIRED | J57: Build | K57: Honest bands. Rare among competitors and pre-qualifies leads
A58: /team/ | B58: / | C58: Team | D58: P0 | E58: - | F58: - | G58: Global | H58: - | I58: Confirmed | J58: Build
A59: /team/{person-slug}/ | B59: /team/ | C59: Person | D59: P1 | E59: - | F59: - | G59: Global | H59: - | I59: DATA REQUIRED | J59: Build | K59: Only index profiles with real credentials. Competitor profiles average 123 words, which is easy to beat
A60: /careers/ | B60: / | C60: Company | D60: P2 | E60: - | F60: - | G60: NP | H60: - | I60: Confirmed | J60: Keep
A61: /contact/ | B61: / | C61: Conversion | D61: P0 | E61: - | F61: - | G61: Global | H61: - | I61: Confirmed | J61: Build
A62: /project-enquiry/ | B62: / | C62: Conversion | D62: P0 | E62: - | F62: - | G62: Global | H62: - | I62: Confirmed | J62: Build | K62: The primary conversion asset. Every commercial page links here
A63: /project-enquiry/thank-you/ | B63: /project-enquiry/ | C63: Conversion | D63: P0 | E63: - | F63: - | G63: Global | H63: - | I63: Confirmed | J63: Build | K63: Noindex. Fires the generate_lead event
A64: /book-a-call/ | B64: / | C64: Conversion | D64: P1 | E64: - | F64: - | G64: Global | H64: - | I64: Confirmed | J64: Build | K64: Timezone-aware scheduling is essential given the time difference
A65: /privacy-policy/ /terms/ /cookie-policy/ | B65: / | C65: Legal | D65: P0 | E65: - | F65: - | G65: Global | H65: - | I65: Confirmed | J65: Build | K65: Required for UK/EU/AU visitors and for buyer due diligence
A66: /locations/* country pages | B66: / | C66: Geo | D66: P3 | E66: - | F66: - | G66: US/AU/UK | H66: - | I66: - | J66: Do not build yet | K66: No local presence means a lower ceiling than local competitors. Only build if each page carries genuinely market-specific substance
A69: Page counts (formula-driven)
A70: P0 pages | B70: =COUNTIF(D4:D66,"P0") -> 16
A71: P1 pages | B71: =COUNTIF(D4:D66,"P1") -> 20
A72: P2 pages | B72: =COUNTIF(D4:D66,"P2") -> 22
A73: P3 pages | B73: =COUNTIF(D4:D66,"P3") -> 4
A74: Capability-gated (blocked) | B74: =COUNTIF(I4:I66,"GATED") -> 8
A75: Rows needing data from Hiver | B75: =COUNTIF(I4:I66,"DATA REQUIRED") -> 24

Sheet 10 Page SEO
A1: Page-level SEO: titles, descriptions, H1s
A2: Every title is under 60 characters and every description under 155, unlike 122 of the 253 competitor titles. Copy is a first draft for review, not final.
A3: URL | B3: Title tag | C3: Meta description | D3: H1 | E3: Primary keyword | F3: Secondary keywords | G3: Schema | H3: Primary CTA
A4: / | B4: Hiver Technology | Web, App & CRM Development Team | C4: Custom web applications, WordPress builds, mobile apps and CRM systems, delivered by a senior team in Nepal for clients in the US, UK and Australia. | D4: Software, web and CRM builds for growing businesses | E4: hiver technology | F4: custom software development; web application development; dedicated development team | G4: Organization, WebSite, BreadcrumbList | H4: Start a project
A5: /services/ | B5: Development & Marketing Services | Hiver Technology | C5: Web applications, WordPress, CRM systems, mobile apps, integrations and marketing automation. See what each engagement includes and what it costs. | D5: What we build, and how each engagement runs | E5: software development services | F5: web development services; crm development; integration services | G5: WebPage, BreadcrumbList, ItemList | H5: Discuss your project
A6: /services/web-application-development/ | B6: Custom Web Application Development | Hiver Technology | C6: Custom web applications built around your actual workflow, from discovery to launch and support. Fixed-scope stages, senior developers, code you own. | D6: Custom web applications built around how your business actually works | E6: custom web application development | F6: web app development services; custom software development; saas development | G6: WebPage, Service, BreadcrumbList, FAQPage | H6: Request a technical scope
A7: /services/crm-development/ | B7: Custom CRM Development & Integration | Hiver Technology | C7: Custom CRM systems and integrations for teams that have outgrown spreadsheets or off-the-shelf tools. Built to fit your pipeline, not the other way round. | D7: Custom CRM systems for teams that have outgrown off-the-shelf tools | E7: custom crm development | F7: crm integration services; custom crm software; crm development company | G7: WebPage, Service, BreadcrumbList, FAQPage | H7: Request a CRM scope
A8: /services/wordpress-development/ | B8: WordPress Development Company | Hiver Technology | C8: WordPress builds without page-builder bloat: custom themes, clean code, fast Core Web Vitals and a CMS your team can actually use. | D8: WordPress builds without the page-builder bloat | E8: wordpress development company | F8: wordpress development agency; custom wordpress theme; wordpress developers | G8: WebPage, Service, BreadcrumbList, FAQPage | H8: Request a build estimate
A9: /services/dedicated-development-team/ | B9: Hire a Dedicated Development Team | Hiver Technology | C9: Senior developers working as an extension of your team, with real timezone overlap, named people and clear contracts. Monthly, not per-ticket. | D9: A senior development team that works as an extension of yours | E9: hire dedicated development team | F9: hire dedicated developers; offshore development team; staff augmentation | G9: WebPage, Service, BreadcrumbList, FAQPage | H9: Discuss team requirements
A10: /services/wordpress-maintenance/ | B10: WordPress Maintenance & Support Plans | Hiver Technology | C10: Ongoing WordPress maintenance: updates, backups, security, uptime and performance monitoring, with a named contact and a monthly report. | D10: WordPress maintenance with a named contact and a real report | E10: wordpress maintenance and support plans | F10: wordpress support plans; wordpress care plan; wordpress security monitoring | G10: WebPage, Service, BreadcrumbList, FAQPage | H10: Compare support plans
A11: /services/wordpress-performance-optimisation/ | B11: WordPress Core Web Vitals & Speed Fixes | Hiver Technology | C11: Diagnose and fix what is actually slowing your WordPress site: render-blocking assets, bloated builders, unoptimised images and hosting limits. | D11: Fix what is actually slowing your WordPress site | E11: wordpress core web vitals fix | F11: wordpress speed optimisation; improve lcp wordpress; wordpress inp | G11: WebPage, Service, BreadcrumbList, FAQPage | H11: Request a performance audit
A12: /services/marketing-automation/ | B12: Lifecycle Email & Marketing Automation | Hiver Technology | C12: Welcome, nurture, win-back and cart-recovery flows built on your CRM and email platform, with the reporting to show what each one earns. | D12: Lifecycle email and automation that reports what it earns | E12: lifecycle email marketing services | F12: marketing automation agency; email automation; crm follow up automation; abandoned cart automation | G12: WebPage, Service, BreadcrumbList, FAQPage | H12: Request an automation review
A13: /services/integrations/ | B13: Custom API & System Integration Development | Hiver Technology | C13: Connect the systems you already run: CRM, ERP, accounting, marketing and storefronts. Custom-mapped, error-checked, monitored data flows. | D13: Connect the systems you already run | E13: custom api integration development | F13: system integration services; api development; crm erp integration | G13: WebPage, Service, BreadcrumbList | H13: Scope an integration
A14: /about/ | B14: About Hiver Technology | Our Team & How We Work | C14: Hiver Technology is a software team based in Lalitpur, Nepal, building web applications, CRM systems and websites for clients in the US, UK and Australia. | D14: A senior software team in Nepal, working with clients worldwide | E14: hiver technology | F14: hiver technology nepal; about hiver technology; software company nepal | G14: AboutPage, Organization, BreadcrumbList | H14: Meet the team
... A18: /project-enquiry/ | B18: Start a Project | Hiver Technology | C18: Tell us what you need, your platform, timeline and budget band. A senior developer reviews every enquiry and replies within one business day. | D18: Tell us about your project | E18: - | F18: - | G18: WebPage, BreadcrumbList | H18: Submit enquiry

Sheet 11 Content Briefs
A1: Content briefs - P0 and P1 pages
A2: One block per page. Blockers marked DATA REQUIRED must be cleared before writing.
A4: BRIEF: /services/dedicated-development-team/
A5: URL | B5: /services/dedicated-development-team/
A6: Priority | B6: P0
A7: Primary keyword | B7: hire dedicated development team
A8: Secondary keywords | B8: hire dedicated developers; offshore development team; staff augmentation; extended engineering team
A9: Search intent | B9: Transactional. Buyer has decided to add capacity and is comparing suppliers and models.
A10: Target audience | B10: CTO, engineering manager or founder at a US/UK/AU company with more roadmap than developers.
A11: Target country | B11: US primary, UK and AU secondary
A12: Business goal | B12: Qualified enquiry for a monthly team engagement. Highest-margin, most repeatable revenue available to Hiver.
A13: Winnability tier | B13: B
A14: Word count | B14: 1,400-1,700
A15: H2 structure | B15: 1. The problem: roadmap outpacing hiring | 2. What a dedicated team actually means (and what it does not) | 3. Who you get: named seniors, not a rotating pool | 4. How overlap works: real hours, not 'flexible' | 5. How we run the engagement: standups, sprints, reporting, escalation | 6. Contracts, IP and NDAs | 7. Security and access control | 8. What it costs and what changes the number | 9. Where this is a bad fit | 10. FAQs | 11. Related services | 12. CTA
A16: FAQ topics | B16: What timezone overlap do we actually get? Who owns the code and IP? What happens if a developer leaves? How do you handle NDAs and data protection? What is the minimum engagement? How do you handle quality and code review? What if we need to scale down?
... A22: Blockers | B22: Needs real rate bands, real named seniors with CVs, and Hiver's actual overlap commitment. DATA REQUIRED.
A24: BRIEF: /services/web-application-development/
A25: URL | B25: /services/web-application-development/
A26: Priority | B26: P0
A27: Primary keyword | B27: custom web application development
A28: Secondary keywords | B28: web app development services; custom software development; internal tools development
A29: Search intent | B29: Transactional but research-heavy. Buyer is scoping a build and comparing partners.
A30: Target audience | B30: Operations or product lead at a mid-sized business with a process that spreadsheets no longer handle.
A31: Target country | B31: US primary
A32: Business goal | B32: Scoped technical enquiry. Anchor page for the whole services cluster.
A33: Winnability tier | B33: C
A34: Word count | B34: 1,400-1,600
A35: H2 structure | B35: 1. When a custom application is the right call (and when it is not) | 2. The problems we usually get called about | 3. What we build: internal tools, portals, dashboards, workflow systems | 4. Our stack and why | 5. How a build runs, stage by stage | 6. What you get at each stage | 7. Testing and handover | 8. What a build costs | 9. Case study | 10. FAQs | 11. Related services | 12. CTA
A36: FAQ topics | B36: How long does a build take? What does it cost? Do we own the code? What happens after launch? Can you work with our existing systems? Who maintains it? What if requirements change mid-build?
... A42: Blockers | B42: Needs one referenceable web-app project and real cost bands. DATA REQUIRED.
A44: BRIEF: /services/crm-development/
A45: URL | B45: /services/crm-development/
A46: Priority | B46: P0
A47: Primary keyword | B47: custom crm development
A48: Secondary keywords | B48: crm integration services; custom crm software; crm development company
A49: Search intent | B49: Transactional. Buyer is frustrated with an existing CRM or has outgrown spreadsheets.
A50: Target audience | B50: Sales or operations director carrying a broken pipeline process.
A51: Target country | B51: US primary, UK secondary
A52: Business goal | B52: Highest average deal value among Hiver's confirmed capabilities.
A53: Winnability tier | B53: B
A54: Word count | B54: 1,300-1,500
A55: H2 structure | B55: 1. The symptoms: where off-the-shelf CRM breaks down | 2. Build vs configure vs integrate: how to choose | 3. What we build | 4. What we integrate with | 5. Data migration and clean-up | 6. How the project runs | 7. Adoption: the part most CRM projects fail on | 8. What it costs | 9. FAQs | 10. Related services | 11. CTA
A56: FAQ topics | B56: Should we build or buy? Can you migrate our existing CRM data? How do you handle user adoption? What does it integrate with? What does it cost to run? Who owns the data?
... A62: Blockers | B62: Needs a real CRM project reference. DATA REQUIRED.
A64: BRIEF: /services/integrations/wordpress-hubspot/
A65: URL | B65: /services/integrations/wordpress-hubspot/
A66: Priority | B66: P1
A67: Primary keyword | B67: wordpress hubspot integration
A68: Secondary keywords | B68: hubspot wordpress forms sync; hubspot crm integration; wordpress crm sync
A69: Search intent | B69: Transactional and highly specific. Buyer has both systems and a broken or missing connection.
A70: Target audience | B70: Marketing operations lead.
A71: Target country | B71: US primary
A72: Business goal | B72: Prove the integration-page pattern. Cheapest page type to produce with the clearest winnability.
A73: Winnability tier | B73: A
A74: Word count | B74: 900-1,100
A75: H2 structure | B75: 1. The manual cost of not integrating | 2. What syncs, and which direction | 3. What a proper integration covers | 4. How we build it | 5. Error handling, retries and monitoring | 6. What it costs | 7. FAQs | 8. Related services | 9. CTA
A76: FAQ topics | B76: Can data sync both ways? What happens to consent and marketing permissions? How often does it sync? What happens when the API fails? Do we need a HubSpot paid tier?
... A82: Blockers | B82: Only publish if Hiver has actually built this integration. DATA REQUIRED.
A84: BRIEF: /insights/offshore-vs-onshore-development/
A85: URL | B85: /insights/offshore-vs-onshore-development/
A86: Priority | B86: P1
A87: Primary keyword | B87: offshore vs onshore development agency
A88: Secondary keywords | B88: offshore development risks; nearshore vs offshore; hiring an overseas dev team
A89: Search intent | B89: Commercial investigation. Buyer is weighing the model, not the vendor.
A90: Target audience | B90: Buyer who has been warned off offshore delivery and is looking for an honest assessment.
A91: Target country | B91: AU primary, UK and US secondary
A92: Business goal | B92: Meet the central objection with evidence instead of marketing, then route to the dedicated-team page.
A93: Winnability tier | B93: A
A94: Word count | B94: 1,700-2,000
A95: H2 structure | B95: 1. Why the objection exists and where it is fair | 2. What actually goes wrong (and the pattern behind it) | 3. The four models compared: in-house, local agency, offshore agency, dedicated offshore team | 4. What to ask any overseas supplier | 5. Contract, IP and data protection checklist | 6. Where offshore is genuinely the wrong answer | 7. How we work, and what we will not claim | 8. FAQs | 9. CTA
A96: FAQ topics | B96: Is offshore development cheaper overall? How do you handle timezone gaps? What about IP and data protection? How do I verify a supplier's team is real? When should I hire locally instead?
... A102: Blockers | B102: Needs a real named author with credentials. Do not publish under 'superadmin'.
A104: BRIEF: /works/{first-case-study}/
A105: URL | B105: /works/{first-case-study}/
A106: Priority | B106: P0
A107: Primary keyword | B107: -
A108: Secondary keywords | B108: -
A109: Search intent | B109: Proof asset. Read by buyers already considering Hiver.
A110: Target audience | B110: Every commercial visitor.
A111: Target country | B111: Global
A112: Business goal | B112: Unblock every other commercial page. Nothing on this site converts without one of these.
A113: Winnability tier | B113: n/a
A114: Word count | B114: 900-1,300 (competitor median is 399, so depth is the differentiator)
A115: H2 structure | B115: H1 as a specific outcome sentence | Metric strip (verified only) | Client, industry, market, services, duration | The problem | Constraints | What we did, numbered | Technical decisions and why | What we measured | The outcome | What we would do differently | Client testimonial | Related services | CTA
A116: FAQ topics | B116: n/a
... A122: Blockers | B122: HARD BLOCKER: needs a named client with written permission, verified metrics, and a real testimonial. Do not fabricate or estimate any figure. DATA REQUIRED FROM HIVER.

Sheet 12 Content Calendar
A1: Six-month content calendar
A2: Sequenced by winnability, not by topic appeal. Two articles a month; halve it rather than publishing filler if capacity is short.
A3: Month | B3: Week | C3: Working title | D3: Primary keyword | E3: Intent | F3: Funnel stage | G3: Target URL | H3: Cluster | I3: Priority | J3: Words | K3: Dependency
A4: Month 1 | B4: W1 | C4: Custom CRM development cost: what drives the number | D4: custom crm development cost | E4: Commercial | F4: Mid | G4: /insights/custom-crm-development-cost/ | H4: CRM | I4: P1 | J4: 1,600-1,900 | K4: Needs Hiver's real pricing bands
A5: Month 1 | B5: W3 | C5: Offshore vs onshore development: an honest comparison | D5: offshore vs onshore development agency | E5: Commercial | F5: Mid | G5: /insights/offshore-vs-onshore-development/ | H5: Dedicated team | I5: P1 | J5: 1,700-2,000 | K5: Named author required
A6: Month 2 | B6: W1 | C6: What a dedicated developer actually costs per month | D6: dedicated developer monthly cost | E6: Commercial | F6: Mid | G6: /insights/dedicated-developer-cost/ | H6: Dedicated team | I6: P1 | J6: 1,400-1,700 | K6: Needs real rate bands
A7: Month 2 | B7: W3 | C7: Custom CRM vs off-the-shelf: a decision framework | D7: build a custom crm instead of salesforce | E7: Informational | F7: Upper-mid | G7: /insights/custom-crm-vs-off-the-shelf/ | H7: CRM | I7: P1 | J7: 1,600-1,900 | K7: -
A8: Month 3 | B8: W1 | C8: WordPress website cost: real ranges by scope | D8: wordpress website cost | E8: Commercial | F8: Mid | G8: /insights/wordpress-website-cost/ | H8: WordPress | I8: P1 | J8: 1,500-1,800 | K8: Needs real pricing
A9: Month 3 | B9: W3 | C9: Website migration SEO checklist (written during our own migration) | D9: website migration seo checklist | E9: Informational | F9: Upper | G9: /insights/website-migration-seo-checklist/ | H9: SEO | I9: P1 | J9: 1,800-2,200 | K9: Write during the .com.np migration; first-party experience is the differentiator
A10: Month 4 | B10: W1 | C10: Elementor to a custom theme: what changes and what it costs | D10: elementor to custom theme migration | E10: Commercial | F10: Mid | G10: /insights/elementor-to-custom-theme/ | H10: WordPress | I10: P2 | J10: 1,500-1,800 | K10: Draw on Hiver's own rebuild
A11: Month 4 | B11: W3 | C11: Mobile app development cost: by platform and complexity | D11: mobile app development cost | E11: Commercial | F11: Mid | G11: /insights/mobile-app-development-cost/ | H11: Mobile | I11: P2 | J11: 1,600-1,900 | K11: Needs real pricing
A12: Month 5 | B12: W1 | C12: WordPress vs Webflow vs a custom build | D12: wordpress vs webflow vs custom | E12: Informational | F12: Upper | G12: /insights/wordpress-vs-webflow-vs-custom/ | H12: WordPress | I12: P2 | J12: 1,700-2,000 | K12: -
A13: Month 5 | B13: W3 | C13: Choosing school management software: a buyer's checklist | D13: school management software checklist | E13: Commercial | F13: Mid | G13: /insights/school-management-software-checklist/ | H13: Products | I13: P2 | J13: 1,700-2,000 | K13: Confirm product status first
A14: Month 6 | B14: W1 | C14: Fixing Core Web Vitals on a page-builder site | D14: wordpress core web vitals fix | E14: Informational | F14: Upper-mid | G14: /insights/wordpress-core-web-vitals/ | H14: WordPress | I14: P2 | J14: 1,700-2,000 | K14: Use before/after from Hiver's own site
A15: Month 6 | B15: W3 | C15: What to ask any development agency before you sign | D15: questions to ask a development agency | E15: Commercial | F15: Mid | G15: /insights/questions-to-ask-a-development-agency/ | H15: Trust | I15: P2 | J15: 1,600-1,900 | K15: Competitor proves this format works

Sheet 13 Internal Links
A1: Internal linking plan
A2: The competitor sends a median of 248 internal links per page and 1,129 to its enquiry form. Hiver currently has almost none, because nav links point to '#'.
A3: Source | B3: Target | C3: Suggested anchor | D3: Relationship | E3: Placement | F3: Note
A4: / (home) | B4: /services/web-application-development/ | C4: custom web application development | D4: Home to service | E4: Services section | F4: Vary anchors across the site; do not repeat exact-match everywhere
A5: / (home) | B5: /services/dedicated-development-team/ | C5: work with a dedicated team | D5: Home to service | E5: Services section
A6: /services/ | B6: each service child | C6: descriptive service name plus outcome | D6: Hub to child | E6: Hub cards with 40-60 words each | F6: Never a bare link grid
A7: Every service page | B7: /project-enquiry/ | C7: intent-matched CTA text | D7: Service to conversion | E7: Hero, mid-page, pre-FAQ, footer | F7: Competitor sends 1,129 internal links to its enquiry page. Match the behaviour, not the query-string sprawl
A8: Every service page | B8: relevant /works/ case study | C8: the project name plus the outcome | D8: Service to proof | E8: Proof section | F8: Blocked until a case study exists
A9: Every service page | B9: 2-4 sibling services | C9: sibling service name | D9: Service to service | E9: Related services block | F9: Caps sideways link volume; avoids diluting the hub
A10: /services/integrations/ | B10: each integration child | C10: System A + System B integration | D10: Hub to child | E10: Integration index
A11: Each integration page | B11: /services/crm-development/ or parent service | C11: the underlying service | D11: Child to parent | E11: Related services
A12: Each insight article | B12: one commercial page | C12: contextual phrase in body copy | D12: Insight to service | E12: Within the relevant section, not only at the end | F12: Editorial in-body links carry more weight than footer links
A13: Each insight article | B13: 2-3 related insights | C13: article title | D13: Insight to insight | E13: Related reading | F13: Builds the cluster
A14: /works/{case study} | B14: services used, industry page | C14: service name | D14: Proof to service | E14: Related services
A15: /industries/{industry} | B15: relevant services and case study | C15: service name in industry context | D15: Industry to service | E15: Solutions section
A16: /about/ | B16: /team/, /about/how-we-work/, /about/security-and-compliance/ | C16: descriptive | D16: Trust cluster | E16: Body
A17: /insights/ hub | B17: cluster pillars | C17: cluster topic | D17: Hub to pillar | E17: Category intros | F17: Give any archive real introductory copy or noindex it. The competitor has 16 thin category pages; do not copy that
A18: Breadcrumbs | B18: every ancestor | C18: page title | D18: Structural | E18: Above H1 on every page | F18: Implement with BreadcrumbList schema

Sheet 14 Technical SEO
A1: Technical SEO specification (WordPress + Elementor)
A2: Developer-ready. T01-T05 are blockers: nothing else is worth doing first.
A3: ID | B3: Area | C3: Requirement | D3: Priority | E3: Why it matters here | F3: Implementation | G3: Status
A4: T01 | B4: Blocking | C4: Remove the 'Under Construction' banner | D4: P0 | E4: Disqualifies every prospect on arrival | F4: Delete the notice bar in Elementor | G4: Not started
A5: T02 | B5: Blocking | C5: Delete all six demo testimonials and the placeholder client logos | D5: P0 | E5: Fabricated endorsements carry FTC/ACCC/CMA exposure | F5: Remove the sections entirely; do not rewrite the names | G5: Not started
A6: T03 | B6: Blocking | C6: Replace every '#' link with a real URL | D6: P0 | E6: No crawlable internal graph exists today | F6: Build the URL structure from the URL Map tab, then wire nav and footer | G6: Not started
A7: T04 | B7: Domain | C7: Resolve the .com.np vs gTLD decision and, if migrating, execute a full 1:1 redirect map | D7: P0 | E7: ccTLD carries a Nepal geographic signal that cannot be overridden in Search Console | F7: Register the gTLD, 301 everything, Change of Address in GSC, resubmit sitemaps, update all profiles and citations | G7: Not started
A8: T05 | B8: URLs | C8: Move root-level blog posts under /insights/ with 301s | D8: P0 | E8: Two competing structures currently coexist | F8: Server-level 301s, no chains, update all internal links | G8: Not started
A9: T06 | B9: URLs | C9: Lowercase, hyphenated, no dates, trailing slash consistent, max depth 3 | D9: P0 | E9: Consistency and crawl efficiency | F9: WordPress permalink settings plus a documented convention | G9: Not started
A10: T07 | B10: Indexation | C10: robots.txt, segmented XML sitemaps, self-referencing canonicals | D10: P0 | E10: Baseline crawl control | F10: Sitemaps split by page type; submit each separately for cleaner coverage reporting | G10: Not started
A11: T08 | B11: Indexation | C11: Noindex thin archives (tag, author, date, paginated), the thank-you page and any staging environment | D11: P0 | E11: The competitor's 16 thin category pages are a mistake to copy | F11: Yoast or Rank Math rules plus password protection on staging | G11: Not started
A12: T09 | B12: Performance | C12: Establish a Core Web Vitals baseline: LCP, INP and CLS from field data | D12: P0 | E12: FID was retired; INP is the responsiveness metric now | F12: PageSpeed Insights field data plus GSC Core Web Vitals report | G12: Not started
A13: T10 | B13: Performance | C13: Evaluate whether Elementor should remain the build layer | D13: P1 | E13: Page builders add DOM and script weight that caps LCP and INP; the site is on Elementor 4.1.4 | F13: Compare Elementor-optimised vs a lightweight block theme; document the trade-off rather than assuming | G13: Not started
A14: T11 | B14: Performance | C14: CDN with edge presence in the US, UK and Australia | D14: P0 | E14: Origin latency from Nepal to target markets is a genuine cost | F14: Cloudflare or equivalent; verify TTFB from each target market, not from Kathmandu | G14: Not started
... A31: T28 | B31: QA | C31: Full copy proof-read: 'Developemnt', 'Transfering', "help's" and 'Insitagram' are live today | D31: P0 | E31: Typos on a homepage targeting premium markets read as low capability | F31: Editorial pass before launch | G31: Not started

Sheet 15 Schema Plan
A1: Structured data plan
A2: The competitor audit detected no structured data on any of its 253 URLs. This is a free differentiator - and entity markup matters more than usual given the brand collision.
A3: Schema type | B3: Where | C3: Key properties | D3: Why | E3: Caution
A4: Organization | B4: Site-wide, in the head | C4: name 'Hiver Technology', url, logo, address (Lalitpur, Nepal), telephone, sameAs (LinkedIn, Clutch, G2, Crunchbase, GitHub) | D4: The primary entity-disambiguation signal. Given the hiverhq.com brand collision this matters more than usual | E4: Use only profiles that actually exist and are verified
A5: WebSite | B5: Homepage | C5: name, url, publisher, potentialAction (SearchAction) if on-site search exists | D5: Site-level identity | E5: Omit SearchAction if there is no search
A6: BreadcrumbList | B6: Every page below the root | C6: itemListElement matching the visible breadcrumb | D6: Improves SERP presentation and reinforces hierarchy | E6: Must mirror the visible breadcrumb exactly
A7: Service | B7: Each service and sub-service page | C7: name, description, provider, areaServed, serviceType | D7: Clarifies commercial page purpose | E7: areaServed should reflect markets Hiver genuinely serves; do not imply local offices
A8: Article | B8: Insight articles and case studies | C8: headline, author (Person), datePublished, dateModified, publisher, image | D8: Author and freshness signals | E8: Requires a real named author. Not valid under 'superadmin'
A9: Person | B9: Team profiles and article authors | C9: name, jobTitle, worksFor, sameAs (LinkedIn), knowsAbout | D9: Author-level E-E-A-T and entity linking | E9: Only for real people with real profiles
A10: SoftwareApplication | B10: Each product page | C10: name, applicationCategory, operatingSystem, offers | D10: The correct type for the school/clinic/dental/HR products | E10: Only if the products genuinely exist as software offerings
A11: FAQPage | B11: Service pages with genuine on-page FAQs | C11: mainEntity question/answer pairs matching visible content | D11: Supports the FAQ block | E11: Only where the FAQs are visible on the page and answer real questions. Never invent FAQs for markup
A12: LocalBusiness | B12: Contact page only | C12: Real Nepal address, hours, geo | D12: Accurate for the actual location | E12: Do not create LocalBusiness entries for the US, UK or AU. Hiver has no offices there
A13: Review / AggregateRating | B13: Not to be used at launch | C13: - | D13: - | E13: FORBIDDEN until real, verifiable, compliantly collected first-party reviews exist. Must never be applied to the current placeholder testimonials

Sheet 16 Trust and E-E-A-T
A1: Trust and E-E-A-T plan
A2: Designed against one specific objection: a US, UK or Australian buyer evaluating a Nepal-based supplier.
A3: Item | B3: Why it matters | C3: Current state | D3: Action | E3: Owner | F3: Priority
A4: Delete placeholder testimonials | B4: Fabricated endorsements are both a credibility and a regulatory problem in all three target markets | C4: Six demo testimonials live | D4: Remove now; replace only with permissioned real ones | E4: Founder | F4: P0
A5: Real client logos with permission | B5: The current strip includes Hiver's own logo and placeholder alt text | C5: Placeholder | D5: Obtain written permission per client | E5: Founder | F5: P0
A6: Named team with real credentials | B6: A remote-delivery buyer needs to see who will actually do the work; the competitor puts its named team on the homepage | C6: Team page exists, thin | D6: Photos, roles, years of experience, specialisms, verified LinkedIn links | E6: Marketing | F6: P0
A7: One deeply documented case study | B7: Nothing else on the site converts without it | C7: None | D7: Choose the strongest completed project and get publication permission | E7: Founder | F7: P0
A8: Verified metrics only | B8: A single invented number destroys the whole document's credibility | C8: n/a | D8: Publish only figures the client has confirmed in writing | E8: Founder | F8: P0
A9: Honest location statement | B9: Obscuring the Nepal base is the fastest way to lose a buyer who finds out later | C9: Address in footer only | D9: State it plainly on About with the international-delivery model explained | E9: Marketing | F9: P0
A10: Transparent pricing bands | B10: Rare among competitors, pre-qualifies leads, and reduces wasted calls | C10: None | D10: Publish honest bands per engagement type | E10: Founder | F10: P1
A11: NDA and IP assignment clarity | B11: The first question a technical buyer asks an overseas supplier | C11: Unknown | D11: Document the process and the standard contract position | E11: Founder | F11: P1
A12: Data protection position (GDPR/DPA) | B12: Required by UK and EU buyers; often a procurement gate | C12: Unknown | D12: Publish the DPA position and any data-residency options | E12: Founder | F12: P1
A13: Security practices | B13: Access control, device policy, code review, secrets handling | C13: Unknown | D13: Publish a short, factual security overview | E13: Dev lead | F13: P1
A14: Timezone overlap commitment | B14: The main practical objection to remote delivery | C14: Unknown | D14: State the actual guaranteed overlap hours per market | E14: Founder | F14: P1
... A23: Legal pages: privacy, terms, cookies | B23: Required and checked by buyers | C23: Footer links dead | D23: Publish real policies | E23: Founder | F23: P0

Sheet 17 Conversion
A1: Conversion and lead generation
A2: Largely modelled on the competitor's three-step conditional enquiry form, which is the strongest single conversion asset in the audited dataset.
A3: Element | B3: Recommendation | C3: Rationale | D3: Source
A4: Primary conversion | B4: A scoped project enquiry at /project-enquiry/ | C4: The competitor sends more internal links here than to any other page, including the homepage | D4: [VERIFIED-FILE]
A5: Secondary conversions | B5: Book a discovery call; request a technical scope; request an audit | C5: Different page intents need different asks | D5: [VERIFIED-FILE]
A6: Form structure | B6: Three steps: (1) what you need, (2) about your business, (3) contact | C6: The competitor's three-step conditional form is the strongest single conversion asset in the dataset | D6: [VERIFIED-FILE]
A7: Step 1 fields | B7: Multi-select service need, with an 'not sure' option | C7: Routing plus qualification in one question | D7: [VERIFIED-FILE]
A8: Step 2 fields | B8: Current website URL (optional), current platform, company size or revenue band, budget band, desired start date, target market | C8: Budget and timeline bands filter out unqualified enquiries before a call is booked | D8: [VERIFIED-FILE]
A9: Step 3 fields | B9: Name, work email, company, country, project description | C9: Keep to the minimum needed to reply | D9: [STRATEGIC-JUDGEMENT]
A10: Conditional qualifiers | B10: Show 3-5 extra fields based on the service selected (e.g. integration: which systems, which direction, how often) | C10: Depth without length; the buyer only sees what applies to them | D10: [VERIFIED-FILE]
A11: Budget bands | B11: Publish bands rather than asking for an open number; include a 'need guidance' option | C11: Anchors expectations and reduces mismatched enquiries | D11: [VERIFIED-FILE]
A12: Disqualification | B12: State the minimum viable engagement plainly on the pricing page and in the form intro | C12: High-volume unqualified enquiry is a failure state, not a win | D12: [STRATEGIC-JUDGEMENT]
A13: Response commitment | B13: 'A senior developer reviews every enquiry and replies within one business day' - only if true | C13: The competitor makes this promise; it converts, but only if honoured | D13: [VERIFIED-FILE]
A14: CTA placement | B14: Hero, after the solution section, after proof, before FAQ, in the footer | C14: Five placements without popups | D14: [STRATEGIC-JUDGEMENT]
... A19: Avoid | B19: Exit popups, chat bait, fake urgency, countdowns, 'free audit' offers with no substance | C19: Erodes the credibility the rest of the site is trying to build | D19: [STRATEGIC-JUDGEMENT]

Sheet 18 Analytics
A1: Measurement and event plan
A2: Closed-loop attribution is the difference between judging this programme on leads and judging it on traffic.
A3: Event / metric | B3: Definition | C3: Where | D3: Priority
A4: generate_lead | B4: Enquiry form submitted successfully | C4: Thank-you page and form callback | D4: P0
A5: form_start | B5: First field interaction on the enquiry form | C5: Enquiry page | D5: P0
A6: form_step_complete | B6: Each step of the three-step form completed, with step number | C6: Enquiry page | D6: P1
A7: form_abandon | B7: Form started, step not completed within the session | C7: Enquiry page | D7: P1
A8: book_call | B8: Booking confirmed in the scheduler | C8: Booking page | D8: P0
A9: request_audit | B9: Audit or assessment request submitted | C9: Service pages | D9: P1
A10: cta_click | B10: Any primary or secondary CTA click, with page and CTA label parameters | C10: Site-wide | D10: P0
A11: email_click | B11: mailto click | C11: Site-wide | D11: P1
A12: phone_click | B12: tel click | C12: Site-wide | D12: P1
A13: whatsapp_click | B13: WhatsApp contact click | C13: Site-wide | D13: P2
A14: scroll_75 | B14: 75% scroll depth on commercial and article pages | C14: Site-wide | D14: P2
... A23: Leading indicators (first 90 days) | B23: Indexation, impressions, first ranking positions, first enquiries. Not revenue | C23: GSC plus GA4 | D23: P0

Sheet 19 Backlinks
A1: Link acquisition and distribution plan
A2: For agency buying, review platforms often occupy the commercial SERP. Treat them as a primary channel, not an afterthought.
A3: Category | B3: Targets | C3: Relevance | D3: Approach | E3: Effort | F3: Priority
A4: Review and directory platforms | B4: Clutch, GoodFirms, DesignRush, G2, Upwork | C4: High | D4: Complete profiles fully; collect verified reviews from real clients | E4: Low | F4: P0
A5: Entity and knowledge graph | B5: LinkedIn company page, Crunchbase, GitHub organisation, founder profiles | C5: High | D5: Consistent naming and details; link with Organization sameAs | E5: Low | F5: P0
A6: Platform ecosystems | B6: WordPress plugin/theme repositories, Shopify Partner directory (if capability confirmed) | C6: High | D6: Contribute something real: a plugin, a theme, documented fixes | E6: Medium | F6: P1
A7: Local and national coverage | B7: Nepal tech press, startup and business media, university and community programmes | C7: Medium | D7: Genuinely easier to earn than US/UK/AU coverage, and links are links | E7: Low | F7: P1
A8: Client and partner links | B8: Portfolio clients, technology partners, suppliers | C8: Medium | D8: Request a credit link where the client is willing | E8: Low | F8: P1
A9: Founder thought leadership | B9: Podcasts, interviews, developer community talks, conference listings | C9: Medium | D9: Pitch a specific, evidenced angle rather than a general introduction | E9: Medium | F9: P1
A10: Original research or teardown | B10: A data study or technical teardown worth citing | C10: High | D10: The only reliable link-earning asset available to a new domain. Needs a real dataset | E10: High | F10: P2
A11: Editorial contributions | B11: Reputable industry publications in the target markets | C11: Medium | D11: Genuine expert contributions only, on topics Hiver can evidence | E11: High | F11: P2
A12: FORBIDDEN | B12: Paid link networks, PBNs, mass guest posting, comment and forum spam, scaled link exchanges, low-quality directory blasts | C12: n/a | D12: Do not use under any circumstances. The short-term gain does not survive | E12: n/a | F12: Never

Sheet 20 Roadmap
A1: Implementation roadmap - Phase 0 through month 12
A2: Phase 0 is not SEO. It is removing fabricated content and making decisions. Nothing later works without it.
A3: Phase | B3: Window | C3: Workstream | D3: Task | E3: Owner | F3: Dependency | G3: Success measure
A4: Phase 0 | B4: Week 0-2 | C4: Unblock | D4: Remove the construction banner, the demo testimonials and the placeholder logos | E4: Founder | F4: None | G4: Nothing fabricated remains on the site
A5: Phase 0 | B5: Week 0-2 | C5: Unblock | D5: Decide the domain question and the brand-naming question | E5: Founder | F5: Trademark advice | G5: A written decision with reasoning
A6: Phase 0 | B6: Week 0-2 | C6: Unblock | D6: Install GA4, GTM, Search Console (all variants), Bing Webmaster | E6: Dev | F6: None | G6: Baseline data flowing
A7: Phase 0 | B7: Week 0-2 | C7: Unblock | D7: Fill the Data Required register | E7: Founder | F7: None | G7: Every open question answered or explicitly deferred
A8: Phase 1 | B8: Day 1-30 | C8: Technical | D8: Implement the URL structure, redirect map, canonicals, sitemaps, robots, breadcrumbs | E8: Dev | F8: Domain decision | G8: Clean crawl, no chains, no orphans
A9: Phase 1 | B9: Day 1-30 | C9: Technical | D9: Core Web Vitals baseline plus CDN, caching and image pipeline | E9: Dev | F9: Hosting review | G9: LCP, INP and CLS measured and improving
A10: Phase 1 | B10: Day 1-30 | C10: Content | D10: Publish P0 pages: home, 5 core services, about, team, works hub, insights hub, contact, enquiry, legal | E10: Content | F10: Copy approval | G10: All P0 rows in the URL Map are live
A11: Phase 1 | B11: Day 1-30 | C11: Trust | D11: Real team profiles, honest location statement, legal pages | E11: Marketing | F11: Photos and bios | G11: No placeholder content anywhere
A12: Phase 1 | B12: Day 1-30 | C12: Distribution | D12: Create and complete Clutch, LinkedIn, Crunchbase, GoodFirms profiles | E12: Marketing | F12: Company details | G12: Profiles live and consistent
A13: Phase 1 | B13: Day 1-30 | C13: Conversion | D13: Build the three-step enquiry form with conditional qualifiers and event tracking | E13: Dev | F13: Field set sign-off | G13: Test submissions tracked end to end
A14: Phase 2 | B14: Day 31-60 | C14: Proof | D14: Publish the first fully documented case study | E14: Founder | F14: Client permission (BLOCKER) | G14: One case study with verified metrics live
... A27: Phase 5 | B27: Month 7-12 | C27: Operations | D27: Quarterly content refresh cycle and closed-loop reporting review | E27: SEO | F27: CRM data | G27: Page-level pipeline attribution working

Sheet 21 Risks
A1: Risk register and expectation setting
A2: Read alongside the roadmap. No specific ranking or traffic outcome is promised anywhere in this workbook.
A3: Risk | B3: Description | C3: Severity | D3: Mitigation
A4: Domain constraint | B4: The .com.np ccTLD carries a Nepal geographic signal that cannot be overridden for a country-code TLD | C4: High | D4: Migrate to a gTLD before building, or accept a materially lower ceiling on US/AU/UK commercial terms
A5: Brand collision | B5: An established SaaS company owns the 'Hiver' brand search space | C5: High | D5: Standardise on 'Hiver Technology'; never target the bare brand term; take trademark advice
A6: No proof assets | B6: No case studies, no real testimonials, no verifiable metrics | C6: Critical | D6: This blocks conversion regardless of ranking. Securing one permissioned case study is the highest-value action available
A7: Capability mismatch | B7: The brief plans Shopify, SEO and automation pages for services that may not be delivered today | C7: High | D7: Keep every gated page blocked until capability is confirmed. Selling what you cannot deliver is worse than ranking for nothing
A8: Authority gap | B8: A new, near-zero-authority domain cannot compete on head commercial terms in year one | C8: High | D8: Tier A first. Accept that Tier C is a year-two conversation
A9: Thin content risk | B9: Copying the competitor's 69-page service template without the depth to support it | C9: Medium | D9: Build 8-10 strong pages, not 69 weak ones
A10: Capacity risk | B10: The content cadence assumes writing capability Hiver has not confirmed | C10: Medium | D10: Confirm real capacity; halve the calendar rather than publishing filler
A11: Regulatory risk | B11: Fabricated testimonials currently live on the site | C11: High | D11: Remove immediately. This is the most urgent item in the workbook
A12: Measurement blindness | B12: No GA4 or CRM attribution means the programme will be judged on vanity metrics | C12: Medium | D12: Closed-loop attribution in Phase 0-1
A13: Expectation risk | B13: SEO on this footing takes quarters, not weeks | C13: Medium | D13: Agree the leading indicators for the first 90 days in writing before starting

Sheet 22 Data Required
A1: Data required from Hiver
A2: Every dependent recommendation is provisional until these are answered. D09, D14, D17 and D25 block the most work.
A3: ID | B3: Category | C3: What is needed | D3: What it blocks | E3: Priority | F3: Status
A4: D01 | B4: Access | C4: Google Search Console access, 16-month export | D4: Blocks baseline measurement | E4: P0 | F4: Open
A5: D02 | B5: Access | C5: GA4 access, or confirmation that it is not installed | D5: Blocks baseline measurement | E5: P0 | F5: Open
A6: D03 | B6: Access | C6: Hosting, CDN and server details | D6: Blocks the performance plan | E6: P0 | F6: Open
A7: D04 | B7: Access | C7: Ahrefs or Semrush seat, or budget for one | D7: Blocks all volume, difficulty and CPC columns | E7: P0 | F7: Open
A8: D05 | B8: Capability | C8: Which services are genuinely delivered today, and by whom | D8: Determines which pages may exist at all | E8: P0 | F8: Open
A9: D06 | B9: Capability | C9: Shopify track record: stores built, Partner status, Plus experience | D9: Gates the entire Shopify cluster | E9: P0 | F9: Open
A10: D07 | B10: Capability | C10: SEO track record: any client results Hiver can evidence | D10: Gates the SEO service cluster | E10: P0 | F10: Open
A11: D08 | B11: Capability | C11: Integration track record: which systems have actually been connected | D11: Gates each integration page | E11: P1 | F11: Open
A12: D09 | B12: Proof | C12: One completed project with written permission to name the client and publish metrics | D12: The single hardest blocker in this plan | E12: P0 | F12: Open
A13: D10 | B13: Proof | C13: Real testimonials with attribution permission | D13: Replaces the placeholder testimonials | E13: P0 | F13: Open
A14: D11 | B14: Proof | C14: Permissioned client logos | D14: Replaces the placeholder logo strip | E14: P0 | F14: Open
... A28: D25 | B28: Domain | C28: Decision on the .com.np versus gTLD question | D28: Blocks every URL in this workbook | E28: P0 | F28: Open
A31: Open items | B31: =COUNTIF(F4:F28,"Open") -> 25
A32: P0 open items | B32: =COUNTIFS(E4:E28,"P0",F4:F28,"Open") -> 17

Sheet 23 Launch QA
A1: Pre-launch QA checklist
A2: Tick nothing until it is verified on the live site. Mark each row Done or Failed in the Status column.
A3: Stage | B3: Check | C3: Priority | D3: Status
A4: Pre-launch | B4: No 'Under Construction' banner anywhere | C4: P0 | D4: Not checked
A5: Pre-launch | B5: No placeholder testimonials, logos or alt text remain | C5: P0 | D5: Not checked
A6: Pre-launch | B6: No '#' links in nav, footer or body | C6: P0 | D6: Not checked
A7: Pre-launch | B7: Every indexable page has a unique title under 60 characters | C7: P0 | D7: Not checked
A8: Pre-launch | B8: Every indexable page has a unique meta description under 155 characters | C8: P0 | D8: Not checked
A9: Pre-launch | B9: Exactly one H1 per page | C9: P0 | D9: Not checked
A10: Pre-launch | B10: Self-referencing canonical on every page | C10: P0 | D10: Not checked
A11: Pre-launch | B11: Segmented XML sitemaps generated and submitted | C11: P0 | D11: Not checked
A12: Pre-launch | B12: robots.txt correct; no accidental site-wide noindex | C12: P0 | D12: Not checked
A13: Pre-launch | B13: No staging URLs indexed; staging password-protected | C13: P0 | D13: Not checked
A14: Pre-launch | B14: HTTPS everywhere; single canonical host | C14: P0 | D14: Not checked
... A33: Pre-launch | B33: WCAG 2.2 AA scan passed; keyboard navigation manually verified | C33: P1 | D33: Not checked
A36: Checks passed | B36: =COUNTIF(D4:D33,"Done") -> 0
A37: Total checks | B37: =COUNTA(B4:B33) -> 30
A38: Percent complete | B38: =IFERROR(B36/B37,0) -> 0
